Workbook
Name Building_Type_List: Site_Energy_No_Model!$C$30:$C$110
Name Building_Type_Table: Site_Energy_No_Model!$C$30:$Q$110
Name Contract_Date_List: LookupData!$AI$1:$AI$2
Name Contract_Length_List: IFERROR(IF(ISBLANK('Renewable Energy'!$E1),Select_Contract_Length,IF('Renewable Energy'!$E1="Owned","N/A (owned)",Select_Contract_Length)),Select_Contract_Length)
Name Contract_Years: IFERROR('Renewable Energy'!$F1^2/'Renewable Energy'!$F1,IFERROR(VLOOKUP('Renewable Energy'!$F1,Years_Lookup,2,FALSE),1))
Name Default_Cooling_Units: IF(IP_SI_Units="IP Units","Ton Hours","kWh")
Name Default_Elec_Units: IF(IP_SI_Units="IP Units","kWh","kWh")
Name Default_Electricity_No_Model: Site_Energy_No_Model!$J$21
Name Default_Fuel_No_Model: Site_Energy_No_Model!$K$21
Name Default_Fuel_Units: IF(IP_SI_Units="IP Units","therm","kWh")
Name Default_Gen_Type: IFERROR(IF(ISBLANK('Renewable Energy'!$C1),"",VLOOKUP('Renewable Energy'!$C1,Renewable_Source_Table,2,FALSE)),"Electricity")
Name Default_Heating_Units: IF(IP_SI_Units="IP Units","Btu x 10^6","kWh")
Name Default_Renewable_Units: IF(ISBLANK('Renewable Energy'!$C1),"",IFERROR(VLOOKUP('Renewable Energy'!$D1,Site_Energy_Table,3,FALSE),Default_Total_Units))
Name Default_Total_Units: IF(IP_SI_Units="IP Units","Btu x 10^6","MWh")
Name Energy_Units_List: LookupData!$G$2:$G$8
Name Energy_Units_Table: LookupData!$G$2:$H$8
Name IP_SI_Units: Instructions!$J$8
Name LEED_Renewable_Category: LookupData!$A$2:$A$4
Name Lookup_RatingSystem: LookupData!$BJ$2:$BJ$12
Name Lookup_Tier1_Points: LookupData!$AR$3:$AU$53
Name Lookup_Tier2_Points: LookupData!$AS$3:$AU$53
Name Lookup_Tier3_Points: LookupData!$AT$3:$AU$33
Name NA_owned: LookupData!$AE$14:$AE$15
Name Renewable_Location_Table: LookupData!$M$3:$O$6
Name Renewable_Source_Table: LookupData!$V$21:$W$40
Name Select_Contract_Length: LookupData!$AE$2:$AE$14
Name Site_Energy_Table: 'Renewable Energy'!$B$13:$D$17
Name TableRatingSystem: LookupData!$BJ$2:$BK$12
Name Tier1_Location_List: LookupData!$M$4:$M$6
Name Tier1_Procurement_Type: LookupData!$R$2:$R$5
Name Tier1_Renewable_Type: LookupData!$V$2:$V$15
Name Tier2_3_Location_List: LookupData!$N$4:$N$6
Name Tier2_Procurement_Type: LookupData!$S$2:$S$10
Name Tier2_Renewable_Type: LookupData!$Y$2:$Y$9
Name Tier3_Procurement_Type: LookupData!$T$2:$T$10
Name Tier3_Renewable_Type: LookupData!$AA$2:$AA$11
Name Units_Consumption: LookupData!$G$2:$G$8
Name Years_Lookup: LookupData!$AE$2:$AF$14

Sheet Instructions
E3: Renewable Energy Calculator LEED v4.1 EA Credit Renewable Energy
E5: Note: This calculator is for use with Excel for Mac 2011 and Excel 2007 or later.
E7: Step 1.
E8: Unit of measurement | J8: IP units
E9: Note: This selection must match the unit of measurement chosen during project registration.
E11: Step 2.
E12: Select the Rating System | H12: BD+C: New Construction
E15: Step 3.
E16: If an energy model was not completed for EAp Minimum Energy Performance,
E17: complete the Site_Energy_No_Model tab.
E19: Step 4.
E20: Complete the Renewable Energy tab.
E22: Step 4.
E23: Upload the completed spreadsheet to LEED Online. Complete any related summary fields in the LEED credit form with the results of the calculator, and upload all other required documentation.
K26: V04 | M26: UOM
K27: Copyright © 2024 | M27: =IF(J8="IP units",1,2) -> 1
K28: U.S. Green Building Council | M28: IP = 1, SI = 2
K29: All Rights Reserved
K30: Last Updated July 2024 | M30: CONCATENATE
M31: =IF(M27=1,"(sq ft)","(sq m)") -> (sq ft)

Sheet Renewable Energy
B2: Renewable Energy
B5: PROJECT SITE ENERGY USE
B6: If the project has an energy model for EAp Minimum Energy Performance, enter the total proposed annual site energy consumption per energy type (with exceptional calculation method)
B7: from the LEED v4.1 Minimum Energy Performance Calculator (MEPC) Table 12.10.
B9: If the project has no energy model, complete the "Site_Energy_No_Model" tab, and then select "Default_Electricity_No_Model" and "Default_Fuel_No_Model" below.
B11: Energy Type | C11: Proposed Site Energy
C12: (per energy source) | D12: Units | X12: kWh
B13: =LookupData!E2 -> Electricity | C13: =+Default_Electricity_No_Model -> 0 | D13: {=+Default_Elec_Units} -> kWh | X13: =IFERROR(C13*VLOOKUP(D13,Energy_Units_Table,2,FALSE),0) -> 0
B14: =LookupData!E3 -> Fossil Fuel | C14: =+Default_Fuel_No_Model -> 0 | D14: {=+Default_Fuel_Units} -> therm | X14: =IFERROR(C14*VLOOKUP(D14,Energy_Units_Table,2,FALSE),0) -> 0
B15: =LookupData!E4 -> District Cooling | D15: {=+Default_Cooling_Units} -> Ton Hours | X15: =IFERROR(C15*VLOOKUP(D15,Energy_Units_Table,2,FALSE),0) -> 0
B16: =LookupData!E5 -> District Heating | D16: {=+Default_Heating_Units} -> Btu x 10^6 | X16: =IFERROR(C16*VLOOKUP(D16,Energy_Units_Table,2,FALSE),0) -> 0
B17: =LookupData!E6 -> Other | D17: {=+Default_Total_Units} -> Btu x 10^6 | X17: =IFERROR(C17*VLOOKUP(D17,Energy_Units_Table,2,FALSE),0) -> 0
B18: Total | C18: =IFERROR(X18/VLOOKUP(D18,Energy_Units_Table,2,FALSE),0) -> 0 | D18: {=+Default_Total_Units} -> Btu x 10^6 | X18: =SUM(X13:X17) -> 0
B19: Total District Energy | C19: =IFERROR(X19/VLOOKUP(D19,Energy_Units_Table,2,FALSE),0) -> 0 | D19: =D18 -> Btu x 10^6 | X19: =SUM(X15,X16) -> 0
B20: Total Electricity + District Energy | C20: =IFERROR(X20/VLOOKUP(D20,Energy_Units_Table,2,FALSE),0) -> 0 | D20: =D18 -> Btu x 10^6 | X20: =SUM(X13,X15,X16) -> 0
B21: Total Fossil Fuel + Other | C21: =IFERROR(X21/VLOOKUP(D21,Energy_Units_Table,2,FALSE),0) -> 0 | D21: =D18 -> Btu x 10^6 | X21: =SUM(X14+X17) -> 0
B23: RENEWABLE ENERGY GENERATION:
B24: Complete all fields of the table for all renewable energy sources allocated to the project.
B25: Renewable Energy Category | C25: Renewable Energy Type | D25: Energy Offset Type | E25: Renewable Energy Procurement Type | F25: Length of Contract (Years) | G25: Renewable Location | H25: Contract execution date | I25: Generator "New Date" (or date contracted / designed to come online) | J25: Green-e Certified (or equivalent eco-label)? | L25: Annual Renewable Generation (Site Energy) | Q25: Annual Renewable Percent of Site Energy
L26: Annual Renewable Generation (for a one-time purchase enter total purchase amount) | M26: Quantity of annual renewable attributes used to satisfy Renewable Portfolio Standard (RPS) / mandatory renewable capacity policies. (0 if N/A) | N26: Qualifying Annual Renewable Generation with EACs retained | O26: Units of Energy | Q26: Percent of Electricity | R26: Percent of District Energy | S26: Percent of Fossil Fuel + Other | T26: Qualifying Percent of Total Annual Site Energy | W26: kWh - Annual with RECs retained | X26: kWh - Qualifying Annual
A27: =IFERROR(MATCH($B27,LEED_Renewable_Category,0),"") | D27: {=+Default_Gen_Type} | N27: =IFERROR(IF($L27>0,IF(AND($A27=2,$W27>$X$20),IF($J27="Yes",(($L27-$M27)*Contract_Years/10),($X$20/VLOOKUP($O27,Energy_Units_Table,2,FALSE)*Contract_Years/10)),IF(OR($A27=1,$A27=2,$J27="Yes",$C27<>"Electricity"),(($L27-$M27)*Contract_Years/10),"")),""),"") | O27: {=+Default_Renewable_Units} | Q27: =IF(ISBLANK($L27),"",IFERROR(IF($D27="Electricity",IF($A27=1,$X27/$X$13,MIN($X27/$X$13,100%)),""),"")) | R27: =IF(ISBLANK($L27),"",IFERROR(IF($D27="Electricity",MIN(MAX($X27-$X$13,0)/$X$19,100%),IF($D27="Fossil Fuel",MIN(MAX($X27-$X$21,0)/$X$19,100%),MIN($X27/$X$19,100%))),"")) | S27: =IF(ISBLANK($L27),"",IFERROR(IF($D27<>"Electricity",MIN($X27/$X$21,100%),""),"")) | T27: =IFERROR(IF($A27=1,$X27/$X$18,IF(AND($A27=2,$D27="Electricity"),MIN(MIN($X27,$X$20)/$X$18,100%),MIN(IF($D27="Electricity",MIN($X27,$X$20)/$X$18,MIN($X27,$X$19+$X$21)/$X$18),100%))),"") | W27: =IFERROR((L27-M27)*VLOOKUP(O27,Energy_Units_Table,2,FALSE),0) -> 0 | X27: =IFERROR(N27*VLOOKUP(O27,Energy_Units_Table,2,FALSE),0) -> 0 | AA27: =IFERROR(IF(ISBLANK('Renewable Energy'!$B27),"",VLOOKUP('Renewable Energy'!$B27,Renewable_Source_Table,2,FALSE)),"Electricity")
A28: =IFERROR(MATCH($B28,LEED_Renewable_Category,0),"") | D28: {=+Default_Gen_Type} | N28: =IFERROR(IF($L28>0,IF(AND($A28=2,$W28>$X$20),IF($J28="Yes",(($L28-$M28)*Contract_Years/10),($X$20/VLOOKUP($O28,Energy_Units_Table,2,FALSE)*Contract_Years/10)),IF(OR($A28=1,$A28=2,$J28="Yes",$C28<>"Electricity"),(($L28-$M28)*Contract_Years/10),"")),""),"") | O28: {=+Default_Renewable_Units} | Q28: =IF(ISBLANK($L28),"",IFERROR(IF($D28="Electricity",IF($A28=1,$X28/$X$13,MIN($X28/$X$13,100%)),""),"")) | R28: =IF(ISBLANK($L28),"",IFERROR(IF($D28="Electricity",MIN(MAX($X28-$X$13,0)/$X$19,100%),IF($D28="Fossil Fuel",MIN(MAX($X28-$X$21,0)/$X$19,100%),MIN($X28/$X$19,100%))),"")) | S28: =IF(ISBLANK($L28),"",IFERROR(IF($D28<>"Electricity",MIN($X28/$X$21,100%),""),"")) | T28: =IFERROR(IF($A28=1,$X28/$X$18,IF(AND($A28=2,$D28="Electricity"),MIN(MIN($X28,$X$20)/$X$18,100%),MIN(IF($D28="Electricity",MIN($X28,$X$20)/$X$18,MIN($X28,$X$19+$X$21)/$X$18),100%))),"") | W28: =IFERROR((L28-M28)*VLOOKUP(O28,Energy_Units_Table,2,FALSE),0) -> 0 | X28: =IFERROR(N28*VLOOKUP(O28,Energy_Units_Table,2,FALSE),0) -> 0
A29: =IFERROR(MATCH($B29,LEED_Renewable_Category,0),"") | D29: {=+Default_Gen_Type} | N29: =IFERROR(IF($L29>0,IF(AND($A29=2,$W29>$X$20),IF($J29="Yes",(($L29-$M29)*Contract_Years/10),($X$20/VLOOKUP($O29,Energy_Units_Table,2,FALSE)*Contract_Years/10)),IF(OR($A29=1,$A29=2,$J29="Yes",$C29<>"Electricity"),(($L29-$M29)*Contract_Years/10),"")),""),"") | O29: {=+Default_Renewable_Units} | Q29: =IF(ISBLANK($L29),"",IFERROR(IF($D29="Electricity",IF($A29=1,$X29/$X$13,MIN($X29/$X$13,100%)),""),"")) | R29: =IF(ISBLANK($L29),"",IFERROR(IF($D29="Electricity",MIN(MAX($X29-$X$13,0)/$X$19,100%),IF($D29="Fossil Fuel",MIN(MAX($X29-$X$21,0)/$X$19,100%),MIN($X29/$X$19,100%))),"")) | S29: =IF(ISBLANK($L29),"",IFERROR(IF($D29<>"Electricity",MIN($X29/$X$21,100%),""),"")) | T29: =IFERROR(IF($A29=1,$X29/$X$18,IF(AND($A29=2,$D29="Electricity"),MIN(MIN($X29,$X$20)/$X$18,100%),MIN(IF($D29="Electricity",MIN($X29,$X$20)/$X$18,MIN($X29,$X$19+$X$21)/$X$18),100%))),"") | W29: =IFERROR((L29-M29)*VLOOKUP(O29,Energy_Units_Table,2,FALSE),0) -> 0 | X29: =IFERROR(N29*VLOOKUP(O29,Energy_Units_Table,2,FALSE),0) -> 0
A30: =IFERROR(MATCH($B30,LEED_Renewable_Category,0),"") | D30: {=+Default_Gen_Type} | N30: =IFERROR(IF($L30>0,IF(AND($A30=2,$W30>$X$20),IF($J30="Yes",(($L30-$M30)*Contract_Years/10),($X$20/VLOOKUP($O30,Energy_Units_Table,2,FALSE)*Contract_Years/10)),IF(OR($A30=1,$A30=2,$J30="Yes",$C30<>"Electricity"),(($L30-$M30)*Contract_Years/10),"")),""),"") | O30: {=+Default_Renewable_Units} | Q30: =IF(ISBLANK($L30),"",IFERROR(IF($D30="Electricity",IF($A30=1,$X30/$X$13,MIN($X30/$X$13,100%)),""),"")) | R30: =IF(ISBLANK($L30),"",IFERROR(IF($D30="Electricity",MIN(MAX($X30-$X$13,0)/$X$19,100%),IF($D30="Fossil Fuel",MIN(MAX($X30-$X$21,0)/$X$19,100%),MIN($X30/$X$19,100%))),"")) | S30: =IF(ISBLANK($L30),"",IFERROR(IF($D30<>"Electricity",MIN($X30/$X$21,100%),""),"")) | T30: =IFERROR(IF($A30=1,$X30/$X$18,IF(AND($A30=2,$D30="Electricity"),MIN(MIN($X30,$X$20)/$X$18,100%),MIN(IF($D30="Electricity",MIN($X30,$X$20)/$X$18,MIN($X30,$X$19+$X$21)/$X$18),100%))),"") | W30: =IFERROR((L30-M30)*VLOOKUP(O30,Energy_Units_Table,2,FALSE),0) -> 0 | X30: =IFERROR(N30*VLOOKUP(O30,Energy_Units_Table,2,FALSE),0) -> 0
A31: =IFERROR(MATCH($B31,LEED_Renewable_Category,0),"") | D31: {=+Default_Gen_Type} | N31: =IFERROR(IF($L31>0,IF(AND($A31=2,$W31>$X$20),IF($J31="Yes",(($L31-$M31)*Contract_Years/10),($X$20/VLOOKUP($O31,Energy_Units_Table,2,FALSE)*Contract_Years/10)),IF(OR($A31=1,$A31=2,$J31="Yes",$C31<>"Electricity"),(($L31-$M31)*Contract_Years/10),"")),""),"") | O31: {=+Default_Renewable_Units} | Q31: =IF(ISBLANK($L31),"",IFERROR(IF($D31="Electricity",IF($A31=1,$X31/$X$13,MIN($X31/$X$13,100%)),""),"")) | R31: =IF(ISBLANK($L31),"",IFERROR(IF($D31="Electricity",MIN(MAX($X31-$X$13,0)/$X$19,100%),IF($D31="Fossil Fuel",MIN(MAX($X31-$X$21,0)/$X$19,100%),MIN($X31/$X$19,100%))),"")) | S31: =IF(ISBLANK($L31),"",IFERROR(IF($D31<>"Electricity",MIN($X31/$X$21,100%),""),"")) | T31: =IFERROR(IF($A31=1,$X31/$X$18,IF(AND($A31=2,$D31="Electricity"),MIN(MIN($X31,$X$20)/$X$18,100%),MIN(IF($D31="Electricity",MIN($X31,$X$20)/$X$18,MIN($X31,$X$19+$X$21)/$X$18),100%))),"") | W31: =IFERROR((L31-M31)*VLOOKUP(O31,Energy_Units_Table,2,FALSE),0) -> 0 | X31: =IFERROR(N31*VLOOKUP(O31,Energy_Units_Table,2,FALSE),0) -> 0
A32: =IFERROR(MATCH($B32,LEED_Renewable_Category,0),"") | D32: {=+Default_Gen_Type} | N32: =IFERROR(IF($L32>0,IF(AND($A32=2,$W32>$X$20),IF($J32="Yes",(($L32-$M32)*Contract_Years/10),($X$20/VLOOKUP($O32,Energy_Units_Table,2,FALSE)*Contract_Years/10)),IF(OR($A32=1,$A32=2,$J32="Yes",$C32<>"Electricity"),(($L32-$M32)*Contract_Years/10),"")),""),"") | O32: {=+Default_Renewable_Units} | Q32: =IF(ISBLANK($L32),"",IFERROR(IF($D32="Electricity",IF($A32=1,$X32/$X$13,MIN($X32/$X$13,100%)),""),"")) | R32: =IF(ISBLANK($L32),"",IFERROR(IF($D32="Electricity",MIN(MAX($X32-$X$13,0)/$X$19,100%),IF($D32="Fossil Fuel",MIN(MAX($X32-$X$21,0)/$X$19,100%),MIN($X32/$X$19,100%))),"")) | S32: =IF(ISBLANK($L32),"",IFERROR(IF($D32<>"Electricity",MIN($X32/$X$21,100%),""),"")) | T32: =IFERROR(IF($A32=1,$X32/$X$18,IF(AND($A32=2,$D32="Electricity"),MIN(MIN($X32,$X$20)/$X$18,100%),MIN(IF($D32="Electricity",MIN($X32,$X$20)/$X$18,MIN($X32,$X$19+$X$21)/$X$18),100%))),"") | W32: =IFERROR((L32-M32)*VLOOKUP(O32,Energy_Units_Table,2,FALSE),0) -> 0 | X32: =IFERROR(N32*VLOOKUP(O32,Energy_Units_Table,2,FALSE),0) -> 0
A33: =IFERROR(MATCH($B33,LEED_Renewable_Category,0),"") | D33: {=+Default_Gen_Type} | N33: =IFERROR(IF($L33>0,IF(AND($A33=2,$W33>$X$20),IF($J33="Yes",(($L33-$M33)*Contract_Years/10),($X$20/VLOOKUP($O33,Energy_Units_Table,2,FALSE)*Contract_Years/10)),IF(OR($A33=1,$A33=2,$J33="Yes",$C33<>"Electricity"),(($L33-$M33)*Contract_Years/10),"")),""),"") | O33: {=+Default_Renewable_Units} | Q33: =IF(ISBLANK($L33),"",IFERROR(IF($D33="Electricity",IF($A33=1,$X33/$X$13,MIN($X33/$X$13,100%)),""),"")) | R33: =IF(ISBLANK($L33),"",IFERROR(IF($D33="Electricity",MIN(MAX($X33-$X$13,0)/$X$19,100%),IF($D33="Fossil Fuel",MIN(MAX($X33-$X$21,0)/$X$19,100%),MIN($X33/$X$19,100%))),"")) | S33: =IF(ISBLANK($L33),"",IFERROR(IF($D33<>"Electricity",MIN($X33/$X$21,100%),""),"")) | T33: =IFERROR(IF($A33=1,$X33/$X$18,IF(AND($A33=2,$D33="Electricity"),MIN(MIN($X33,$X$20)/$X$18,100%),MIN(IF($D33="Electricity",MIN($X33,$X$20)/$X$18,MIN($X33,$X$19+$X$21)/$X$18),100%))),"") | W33: =IFERROR((L33-M33)*VLOOKUP(O33,Energy_Units_Table,2,FALSE),0) -> 0 | X33: =IFERROR(N33*VLOOKUP(O33,Energy_Units_Table,2,FALSE),0) -> 0
A34: =IFERROR(MATCH($B34,LEED_Renewable_Category,0),"") | D34: {=+Default_Gen_Type} | N34: =IFERROR(IF($L34>0,IF(AND($A34=2,$W34>$X$20),IF($J34="Yes",(($L34-$M34)*Contract_Years/10),($X$20/VLOOKUP($O34,Energy_Units_Table,2,FALSE)*Contract_Years/10)),IF(OR($A34=1,$A34=2,$J34="Yes",$C34<>"Electricity"),(($L34-$M34)*Contract_Years/10),"")),""),"") | O34: {=+Default_Renewable_Units} | Q34: =IF(ISBLANK($L34),"",IFERROR(IF($D34="Electricity",IF($A34=1,$X34/$X$13,MIN($X34/$X$13,100%)),""),"")) | R34: =IF(ISBLANK($L34),"",IFERROR(IF($D34="Electricity",MIN(MAX($X34-$X$13,0)/$X$19,100%),IF($D34="Fossil Fuel",MIN(MAX($X34-$X$21,0)/$X$19,100%),MIN($X34/$X$19,100%))),"")) | S34: =IF(ISBLANK($L34),"",IFERROR(IF($D34<>"Electricity",MIN($X34/$X$21,100%),""),"")) | T34: =IFERROR(IF($A34=1,$X34/$X$18,IF(AND($A34=2,$D34="Electricity"),MIN(MIN($X34,$X$20)/$X$18,100%),MIN(IF($D34="Electricity",MIN($X34,$X$20)/$X$18,MIN($X34,$X$19+$X$21)/$X$18),100%))),"") | W34: =IFERROR((L34-M34)*VLOOKUP(O34,Energy_Units_Table,2,FALSE),0) -> 0 | X34: =IFERROR(N34*VLOOKUP(O34,Energy_Units_Table,2,FALSE),0) -> 0
A35: =IFERROR(MATCH($B35,LEED_Renewable_Category,0),"") | D35: {=+Default_Gen_Type} | N35: =IFERROR(IF($L35>0,IF(AND($A35=2,$W35>$X$20),IF($J35="Yes",(($L35-$M35)*Contract_Years/10),($X$20/VLOOKUP($O35,Energy_Units_Table,2,FALSE)*Contract_Years/10)),IF(OR($A35=1,$A35=2,$J35="Yes",$C35<>"Electricity"),(($L35-$M35)*Contract_Years/10),"")),""),"") | O35: {=+Default_Renewable_Units} | Q35: =IF(ISBLANK($L35),"",IFERROR(IF($D35="Electricity",IF($A35=1,$X35/$X$13,MIN($X35/$X$13,100%)),""),"")) | R35: =IF(ISBLANK($L35),"",IFERROR(IF($D35="Electricity",MIN(MAX($X35-$X$13,0)/$X$19,100%),IF($D35="Fossil Fuel",MIN(MAX($X35-$X$21,0)/$X$19,100%),MIN($X35/$X$19,100%))),"")) | S35: =IF(ISBLANK($L35),"",IFERROR(IF($D35<>"Electricity",MIN($X35/$X$21,100%),""),"")) | T35: =IFERROR(IF($A35=1,$X35/$X$18,IF(AND($A35=2,$D35="Electricity"),MIN(MIN($X35,$X$20)/$X$18,100%),MIN(IF($D35="Electricity",MIN($X35,$X$20)/$X$18,MIN($X35,$X$19+$X$21)/$X$18),100%))),"") | W35: =IFERROR((L35-M35)*VLOOKUP(O35,Energy_Units_Table,2,FALSE),0) -> 0 | X35: =IFERROR(N35*VLOOKUP(O35,Energy_Units_Table,2,FALSE),0) -> 0
A36: =IFERROR(MATCH($B36,LEED_Renewable_Category,0),"") | D36: {=+Default_Gen_Type} | N36: =IFERROR(IF($L36>0,IF(AND($A36=2,$W36>$X$20),IF($J36="Yes",(($L36-$M36)*Contract_Years/10),($X$20/VLOOKUP($O36,Energy_Units_Table,2,FALSE)*Contract_Years/10)),IF(OR($A36=1,$A36=2,$J36="Yes",$C36<>"Electricity"),(($L36-$M36)*Contract_Years/10),"")),""),"") | O36: {=+Default_Renewable_Units} | Q36: =IF(ISBLANK($L36),"",IFERROR(IF($D36="Electricity",IF($A36=1,$X36/$X$13,MIN($X36/$X$13,100%)),""),"")) | R36: =IF(ISBLANK($L36),"",IFERROR(IF($D36="Electricity",MIN(MAX($X36-$X$13,0)/$X$19,100%),IF($D36="Fossil Fuel",MIN(MAX($X36-$X$21,0)/$X$19,100%),MIN($X36/$X$19,100%))),"")) | S36: =IF(ISBLANK($L36),"",IFERROR(IF($D36<>"Electricity",MIN($X36/$X$21,100%),""),"")) | T36: =IFERROR(IF($A36=1,$X36/$X$18,IF(AND($A36=2,$D36="Electricity"),MIN(MIN($X36,$X$20)/$X$18,100%),MIN(IF($D36="Electricity",MIN($X36,$X$20)/$X$18,MIN($X36,$X$19+$X$21)/$X$18),100%))),"") | W36: =IFERROR((L36-M36)*VLOOKUP(O36,Energy_Units_Table,2,FALSE),0) -> 0 | X36: =IFERROR(N36*VLOOKUP(O36,Energy_Units_Table,2,FALSE),0) -> 0
A38: A | B38: Total Tier 1: On-site renewable energy | L38: =IFERROR(LookupData!$BQ$3,"") | M38: Points | N38: =IFERROR(X38/VLOOKUP(O38,Energy_Units_Table,2,FALSE),0) -> 0 | O38: =$D$20 -> Btu x 10^6 | Q38: =IFERROR(SUMIF($A$27:$A$36,1,Q$27:Q$36),"") -> 0 | R38: =IFERROR(SUMIF($A$27:$A$36,1,R$27:R$36),"") -> 0 | S38: =IFERROR(SUMIF($A$27:$A$36,1,S$27:S$36),"") -> 0 | T38: =IFERROR(SUMIF($A$27:$A$36,1,T$27:T$36),"") -> 0 | W38: =MIN(SUMIF($A$27:$A$36,1,$X$27:$X$36),W20) -> 0 | X38: =MIN(SUMIF($A$27:$A$36,1,$X$27:$X$36),X20) -> 0
B39: Total Tier 2. New Off-site renewable electricity | L39: =IFERROR(LookupData!$BR$3,"") | M39: Points | N39: =IFERROR(X39/VLOOKUP(O39,Energy_Units_Table,2,FALSE),0) -> 0 | O39: =$D$20 -> Btu x 10^6 | Q39: =IFERROR(MIN(SUMIF($A$27:$A$36,2,Q$27:Q$36),100%-MIN(Q38,100%)),"") -> 0 | R39: =IFERROR(MIN(SUMIF($A$27:$A$36,2,R$27:R$36),100%-MIN(R38,100%)),"") -> 0 | S39: =IFERROR(MIN(SUMIF($A$27:$A$36,2,S$27:S$36),100%-MIN(S38,100%)),"") -> 0 | T39: =IFERROR(MIN(SUMIF($A$27:$A$36,2,T$27:T$36),100%-MIN(T38,100%)),"") -> 0 | W39: =SUMIF($A$27:$A$36,2,$X$27:$X$36) -> 0 | X39: =SUMIF($A$27:$A$36,2,$X$27:$X$36) -> 0
B40: Total Tier 3. Off-site renewable | L40: =IFERROR(LookupData!$BS$3,"") | M40: Points | N40: =IFERROR(X40/VLOOKUP(O40,Energy_Units_Table,2,FALSE),0) -> 0 | O40: =$D$20 -> Btu x 10^6 | Q40: =IFERROR(MIN(SUMIF($A$27:$A$36,3,Q$27:Q$36),100%-MIN(Q39+Q38,100%)),"") -> 0 | R40: =IFERROR(MIN(SUMIF($A$27:$A$36,3,R$27:R$36),100%-MIN(R39+R38,100%)),"") -> 0 | S40: =IFERROR(MIN(SUMIF($A$27:$A$36,3,S$27:S$36),100%-MIN(S39+S38,100%)),"") -> 0 | T40: =IFERROR(MIN(SUMIF($A$27:$A$36,3,T$27:T$36),100%-MIN(T39+T38,100%)),"") -> 0 | W40: =SUMIF($A$27:$A$36,3,$X$27:$X$36) -> 0 | X40: =SUMIF($A$27:$A$36,3,$X$27:$X$36) -> 0
B42: Total Renewable Energy (Tier 1-3). (Maximum of 5 for BD+C, 6 for ID+C; plus one Exemplary) | L42: =IFERROR(LookupData!$BU$3,"") -> 0 | M42: =IFERROR(IF(LookupData!$BV$3="EP","Points + 1 Exemplary","Points"),"") -> Points | N42: =IFERROR(X42/VLOOKUP(O42,Energy_Units_Table,2,FALSE),0) -> 0 | O42: =$D$20 -> Btu x 10^6 | Q42: =IFERROR(MIN(SUMIF($A$27:$A$36,3,Q$27:Q$36),100%-MIN(Q40+Q39,100%)),"") -> 0 | R42: =IFERROR(MIN(SUMIF($A$27:$A$36,3,R$27:R$36),100%-MIN(R40+R39,100%)),"") -> 0 | S42: =IFERROR(MIN(SUMIF($A$27:$A$36,3,S$27:S$36),100%-MIN(S40+S39,100%)),"") -> 0 | T42: =IFERROR(MIN(SUMIF($A$27:$A$36,3,T$27:T$36),100%-MIN(T40+T39,100%)),"") -> 0 | W42: =SUMIF($A$27:$A$36,3,$X$27:$X$36) -> 0 | X42: =SUMIF($A$27:$A$36,3,$X$27:$X$36) -> 0
B45: Notes:
B46: All environmental attributes associated with renewable energy generation must be retired on behalf of the LEED project in order for the renewable energy procurement to contribute to credit achievement.
B47: Tier 1. On-site renewable energy
B48: a. Documentation for EAp Fundamental Commissioning must be uploaded demonstrating that the on-site renewable system has been installed and commissioned.
B49: b. All renewable combustion sources (agricultural crops, bio-fuel, landfill gas, etc.) must be both captured (harvested) and used on-site to qualify as a Tier 1 renewable energy source.
B50: c. If the project shares on-site renewable sources with other buildings on a campus, and/or is located outside of the project boundary on a contiguous campus sharing ownership with the project owner,
B51: upload signed confirmation from the building owner or owner's representative demonstrating the dedicated allocation to the project building.
B53: Tier 2 and Tier 3: Off-site renewable energy
B54: Off-site renewable energy must be generated by renewable electricity projects located in the same country or geographical region where the LEED project is located.
B55: Tier 2. New Off-site renewable electricity
B56: a. If one-time purchase and delivery of EACs exceeds 100% of the project’s annual electricity use, Green-e certification or equivalent is required.
B57: b. Age of the generation asset(s) is assessed at the beginning of the contract, and the generation asset(s) retain these attributes for the duration of the contract or lease term.
... B110: Project teams must substitute Renewable Energy for both relevant v4 credits, Renewable Energy Production and Green Power and Carbon Offsets, up to a maximum of five points; or up to a maximum of six points for LEED v4 ID+C if also substituting LEED v4.1 ID+C Optimize Energy Performance.

Sheet Site_Energy_No_Model
B2: Renewable Energy
B7: Is the building all-electric (no combustion sources for heating, water heating, cooking, etc. in the project space and base building)? | K7: No
B9: SITE ENERGY DETERMINATION FOR BUILDINGS WITHOUT ENERGY MODELS
B10: Select all building types present in the project, and enter the associated gross area per building type.
B12: Building Type(s) | D12: Area | G12: Site Energy Use Intensity | J12: Annual Site Energy Use
D13: =IF(IP_SI_Units="IP Units","(square feet)","(square meters)") -> (square feet) | G13: =CONCATENATE("Electricity ", IF(IP_SI_Units="IP Units","(kWh/ft2)","(kWh/m2)")) -> Electricity (kWh/ft2) | H13: =CONCATENATE("Natural Gas ", IF(IP_SI_Units="IP Units","(kBtu/ft2)","(kWh/m2)")) -> Natural Gas (kBtu/ft2) | J13: =CONCATENATE("Electricity ", IF(IP_SI_Units="IP Units","(kWh)","(kWh)")) -> Electricity (kWh) | K13: =CONCATENATE("Natural Gas ", IF(IP_SI_Units="IP Units","(therms)","(kWh)")) -> Natural Gas (therms) | M13: =CONCATENATE("Total ", IF(IP_SI_Units="IP Units","(Btu x 10^6)","(MWh)")) -> Total (Btu x 10^6)
G14: =IFERROR(ROUND(IF(IP_SI_Units="IP Units",0.0929,1)*((VLOOKUP($B14,Building_Type_Table,11,FALSE)+IF($K$7="Yes",0.75*VLOOKUP($B14,Building_Type_Table,12,FALSE),0))),2),"") | H14: =IFERROR(ROUND(IF(IP_SI_Units="IP Units",0.0929*3.412,1)*IF(AND($D14>0,$K$7="Yes"),0,VLOOKUP($B14,Building_Type_Table,12,FALSE)),2),"") | J14: =IFERROR($D14*G14,"") | K14: =IFERROR(IF(IP_SI_Units="IP Units",1/100,1)*H14*$D14,"") | M14: =IFERROR(ROUND(IF(IP_SI_Units="IP Units",3.412/1000,1/1000)*J14+IF(IP_SI_Units="IP Units",1/10,1/1000)*K14,1),"")
G15: =IFERROR(ROUND(IF(IP_SI_Units="IP Units",0.0929,1)*((VLOOKUP($B15,Building_Type_Table,11,FALSE)+IF($K$7="Yes",0.75*VLOOKUP($B15,Building_Type_Table,12,FALSE),0))),2),"") | H15: =IFERROR(ROUND(IF(IP_SI_Units="IP Units",0.0929*3.412,1)*IF(AND($D15>0,$K$7="Yes"),0,VLOOKUP($B15,Building_Type_Table,12,FALSE)),2),"") | J15: =IFERROR($D15*G15,"") | K15: =IFERROR(IF(IP_SI_Units="IP Units",1/100,1)*H15*$D15,"") | M15: =IFERROR(ROUND(IF(IP_SI_Units="IP Units",3.412/1000,1/1000)*J15+IF(IP_SI_Units="IP Units",1/10,1/1000)*K15,1),"")
G16: =IFERROR(ROUND(IF(IP_SI_Units="IP Units",0.0929,1)*((VLOOKUP($B16,Building_Type_Table,11,FALSE)+IF($K$7="Yes",0.75*VLOOKUP($B16,Building_Type_Table,12,FALSE),0))),2),"") | H16: =IFERROR(ROUND(IF(IP_SI_Units="IP Units",0.0929*3.412,1)*IF(AND($D16>0,$K$7="Yes"),0,VLOOKUP($B16,Building_Type_Table,12,FALSE)),2),"") | J16: =IFERROR($D16*G16,"") | K16: =IFERROR(IF(IP_SI_Units="IP Units",1/100,1)*H16*$D16,"") | M16: =IFERROR(ROUND(IF(IP_SI_Units="IP Units",3.412/1000,1/1000)*J16+IF(IP_SI_Units="IP Units",1/10,1/1000)*K16,1),"")
G17: =IFERROR(ROUND(IF(IP_SI_Units="IP Units",0.0929,1)*((VLOOKUP($B17,Building_Type_Table,11,FALSE)+IF($K$7="Yes",0.75*VLOOKUP($B17,Building_Type_Table,12,FALSE),0))),2),"") | H17: =IFERROR(ROUND(IF(IP_SI_Units="IP Units",0.0929*3.412,1)*IF(AND($D17>0,$K$7="Yes"),0,VLOOKUP($B17,Building_Type_Table,12,FALSE)),2),"") | J17: =IFERROR($D17*G17,"") | K17: =IFERROR(IF(IP_SI_Units="IP Units",1/100,1)*H17*$D17,"") | M17: =IFERROR(ROUND(IF(IP_SI_Units="IP Units",3.412/1000,1/1000)*J17+IF(IP_SI_Units="IP Units",1/10,1/1000)*K17,1),"")
G18: =IFERROR(ROUND(IF(IP_SI_Units="IP Units",0.0929,1)*((VLOOKUP($B18,Building_Type_Table,11,FALSE)+IF($K$7="Yes",0.75*VLOOKUP($B18,Building_Type_Table,12,FALSE),0))),2),"") | H18: =IFERROR(ROUND(IF(IP_SI_Units="IP Units",0.0929*3.412,1)*IF(AND($D18>0,$K$7="Yes"),0,VLOOKUP($B18,Building_Type_Table,12,FALSE)),2),"") | J18: =IFERROR($D18*G18,"") | K18: =IFERROR(IF(IP_SI_Units="IP Units",1/100,1)*H18*$D18,"") | M18: =IFERROR(ROUND(IF(IP_SI_Units="IP Units",3.412/1000,1/1000)*J18+IF(IP_SI_Units="IP Units",1/10,1/1000)*K18,1),"")
G19: =IFERROR(ROUND(IF(IP_SI_Units="IP Units",0.0929,1)*((VLOOKUP($B19,Building_Type_Table,11,FALSE)+IF($K$7="Yes",0.75*VLOOKUP($B19,Building_Type_Table,12,FALSE),0))),2),"") | H19: =IFERROR(ROUND(IF(IP_SI_Units="IP Units",0.0929*3.412,1)*IF(AND($D19>0,$K$7="Yes"),0,VLOOKUP($B19,Building_Type_Table,12,FALSE)),2),"") | J19: =IFERROR($D19*G19,"") | K19: =IFERROR(IF(IP_SI_Units="IP Units",1/100,1)*H19*$D19,"") | M19: =IFERROR(ROUND(IF(IP_SI_Units="IP Units",3.412/1000,1/1000)*J19+IF(IP_SI_Units="IP Units",1/10,1/1000)*K19,1),"")
G20: =IFERROR(ROUND(IF(IP_SI_Units="IP Units",0.0929,1)*((VLOOKUP($B20,Building_Type_Table,11,FALSE)+IF($K$7="Yes",0.75*VLOOKUP($B20,Building_Type_Table,12,FALSE),0))),2),"") | H20: =IFERROR(ROUND(IF(IP_SI_Units="IP Units",0.0929*3.412,1)*IF(AND($D20>0,$K$7="Yes"),0,VLOOKUP($B20,Building_Type_Table,12,FALSE)),2),"") | J20: =IFERROR($D20*G20,"") | K20: =IFERROR(IF(IP_SI_Units="IP Units",1/100,1)*H20*$D20,"") | M20: =IFERROR(ROUND(IF(IP_SI_Units="IP Units",3.412/1000,1/1000)*J20+IF(IP_SI_Units="IP Units",1/10,1/1000)*K20,1),"")
B21: Total: | D21: =IFERROR(IF(SUM(D14:D20)>0,SUM(D14:D20),""),"") | J21: =IFERROR(IF($D21>0,SUM(J14:J20),""),"") -> 0 | K21: =IFERROR(IF($D21>0,SUM(K14:K20),""),"") -> 0 | M21: =IFERROR(IF($D21>0,SUM(M14:M20),""),"") -> 0 | N21: =IFERROR(IF($D21>0,SUM(N14:N20),""),"") -> 0
B23: ENERGY STAR PortfolioManager Technical Reference - U.S. Energy Use Intensity by Property Type
B24: Source for Total Source EUI and Site EUI (with non-electric sources): https://portfoliomanager.energystar.gov/pdf/reference/US%20National%20Median%20Table.pdf
B25: Electricity and natural gas were calculated based on total source energy and total site energy reported in the ENERGY STAR Portfolio Manager Technical Reference, and source-to-site ratios of 2.80 for electricity and 1.05 for natural gas.
D27: Buildings with non-electric sources serving project (e.g. heating, water heating, and/or cooking) | P27: All-Electric Buildings
D28: IP Units | J28: SI Units | P28: IP Units | Q28: SI Units
D29: Source EUI (kBtu/ft2) | E29: Site EUI (kBtu/ft2) | G29: Electricity (kBtu/ft2) | H29: Natural Gas (kBtu/ft2) | J29: Source EUI (kWh/m2) | K29: Site EUI (kWh/m2) | M29: Electricity (kWh/m2) | N29: Natural Gas (kWh/m2) | P29: Site Energy - Electricity (kWh/ft2) | Q29: Site Energy - Electricity (kWh/m2) | U29: % Electricity
B30: Banking Financial Services | C30: Bank Branch | D30: 209.9 | E30: 88.3 | G30: =(D30-LookupData!$AM$4*E30)/(LookupData!$AM$2-LookupData!$AM$4) -> 66.962857 | H30: =E30-G30 -> 21.337143 | J30: =D30*LookupData!$AN$10 -> 662.17608 | K30: =E30*LookupData!$AN$10 -> 278.56193 | M30: =G30*LookupData!$AN$10 -> 211.24918 | N30: =H30*LookupData!$AN$10 -> 67.312747 | P30: =(M30+N30*0.75)*LookupData!AN$7 -> 24.31586 | Q30: =(M30+N30*0.75) -> 261.73374 | U30: =ROUNDUP(M30/K30,2) -> 0.76
C31: Financial Office | D31: 116.4 | E31: 52.9 | G31: =(D31-LookupData!$AM$4*E31)/(LookupData!$AM$2-LookupData!$AM$4) -> 34.774286 | H31: =E31-G31 -> 18.125714 | J31: =D31*LookupData!$AN$10 -> 367.20961 | K31: =E31*LookupData!$AN$10 -> 166.88478 | M31: =G31*LookupData!$AN$10 -> 109.70319 | N31: =H31*LookupData!$AN$10 -> 57.181584 | P31: =(M31+N31*0.75)*LookupData!AN$7 -> 14.176017 | Q31: =(M31+N31*0.75) -> 152.58938 | U31: =ROUNDUP(M31/K31,2) -> 0.66
B32: Education | C32: Adult Education | D32: 110.4 | E32: 52.4 | G32: =(D32-LookupData!$AM$4*E32)/(LookupData!$AM$2-LookupData!$AM$4) -> 31.645714 | H32: =E32-G32 -> 20.754286 | J32: =D32*LookupData!$AN$10 -> 348.28127 | K32: =E32*LookupData!$AN$10 -> 165.30742 | M32: =G32*LookupData!$AN$10 -> 99.833421 | N32: =H32*LookupData!$AN$10 -> 65.473995 | P32: =(M32+N32*0.75)*LookupData!AN$7 -> 13.836878 | Q32: =(M32+N32*0.75) -> 148.93892 | U32: =ROUNDUP(M32/K32,2) -> 0.61
C33: College_University | D33: 180.6 | E33: 84.3 | G33: =(D33-LookupData!$AM$4*E33)/(LookupData!$AM$2-LookupData!$AM$4) -> 52.62 | H33: =E33-G33 -> 31.68 | J33: =D33*LookupData!$AN$10 -> 569.74274 | K33: =E33*LookupData!$AN$10 -> 265.94304 | M33: =G33*LookupData!$AN$10 -> 166.00146 | N33: =H33*LookupData!$AN$10 -> 99.941583 | P33: =(M33+N33*0.75)*LookupData!AN$7 -> 22.385698 | Q33: =(M33+N33*0.75) -> 240.95764 | U33: =ROUNDUP(M33/K33,2) -> 0.63
C34: K-12 School | D34: 104.4 | E34: 48.5 | G34: =(D34-LookupData!$AM$4*E34)/(LookupData!$AM$2-LookupData!$AM$4) -> 30.557143 | H34: =E34-G34 -> 17.942857 | J34: =D34*LookupData!$AN$10 -> 329.35294 | K34: =E34*LookupData!$AN$10 -> 153.004 | M34: =G34*LookupData!$AN$10 -> 96.399281 | N34: =H34*LookupData!$AN$10 -> 56.604721 | P34: =(M34+N34*0.75)*LookupData!AN$7 -> 12.899849 | Q34: =(M34+N34*0.75) -> 138.85282 | U34: =ROUNDUP(M34/K34,2) -> 0.64
C35: Pre-school _ Daycare | D35: 131.5 | E35: 64.8 | G35: =(D35-LookupData!$AM$4*E35)/(LookupData!$AM$2-LookupData!$AM$4) -> 36.262857 | H35: =E35-G35 -> 28.537143 | J35: =D35*LookupData!$AN$10 -> 414.8459 | K35: =E35*LookupData!$AN$10 -> 204.42597 | M35: =G35*LookupData!$AN$10 -> 114.39922 | N35: =H35*LookupData!$AN$10 -> 90.026744 | P35: =(M35+N35*0.75)*LookupData!AN$7 -> 16.900854 | Q35: =(M35+N35*0.75) -> 181.91928 | U35: =ROUNDUP(M35/K35,2) -> 0.56
C36: Vocational School | D36: 110.4 | E36: 52.4 | G36: =(D36-LookupData!$AM$4*E36)/(LookupData!$AM$2-LookupData!$AM$4) -> 31.645714 | H36: =E36-G36 -> 20.754286 | J36: =D36*LookupData!$AN$10 -> 348.28127 | K36: =E36*LookupData!$AN$10 -> 165.30742 | M36: =G36*LookupData!$AN$10 -> 99.833421 | N36: =H36*LookupData!$AN$10 -> 65.473995 | P36: =(M36+N36*0.75)*LookupData!AN$7 -> 13.836878 | Q36: =(M36+N36*0.75) -> 148.93892 | U36: =ROUNDUP(M36/K36,2) -> 0.61
C37: Other - Education | D37: 110.4 | E37: 52.4 | G37: =(D37-LookupData!$AM$4*E37)/(LookupData!$AM$2-LookupData!$AM$4) -> 31.645714 | H37: =E37-G37 -> 20.754286 | J37: =D37*LookupData!$AN$10 -> 348.28127 | K37: =E37*LookupData!$AN$10 -> 165.30742 | M37: =G37*LookupData!$AN$10 -> 99.833421 | N37: =H37*LookupData!$AN$10 -> 65.473995 | P37: =(M37+N37*0.75)*LookupData!AN$7 -> 13.836878 | Q37: =(M37+N37*0.75) -> 148.93892 | U37: =ROUNDUP(M37/K37,2) -> 0.61
B38: Entertainment / Public Assembly | C38: Convention Center | D38: 109.6 | E38: 56.1 | G38: =(D38-LookupData!$AM$4*E38)/(LookupData!$AM$2-LookupData!$AM$4) -> 28.968571 | H38: =E38-G38 -> 27.131429 | J38: =D38*LookupData!$AN$10 -> 345.7575 | K38: =E38*LookupData!$AN$10 -> 176.97989 | M38: =G38*LookupData!$AN$10 -> 91.387781 | N38: =H38*LookupData!$AN$10 -> 85.592106 | P38: =(M38+N38*0.75)*LookupData!AN$7 -> 14.454028 | Q38: =(M38+N38*0.75) -> 155.58186 | U38: =ROUNDUP(M38/K38,2) -> 0.52
C39: Movie Theater | D39: 112 | E39: 56.2 | G39: =(D39-LookupData!$AM$4*E39)/(LookupData!$AM$2-LookupData!$AM$4) -> 30.28 | H39: =E39-G39 -> 25.92 | J39: =D39*LookupData!$AN$10 -> 353.32883 | K39: =E39*LookupData!$AN$10 -> 177.29536 | M39: =G39*LookupData!$AN$10 -> 95.524973 | N39: =H39*LookupData!$AN$10 -> 81.770386 | P39: =(M39+N39*0.75)*LookupData!AN$7 -> 14.572098 | Q39: =(M39+N39*0.75) -> 156.85276 | U39: =ROUNDUP(M39/K39,2) -> 0.54
C40: Museum | D40: 112 | E40: 56.2 | G40: =(D40-LookupData!$AM$4*E40)/(LookupData!$AM$2-LookupData!$AM$4) -> 30.28 | H40: =E40-G40 -> 25.92 | J40: =D40*LookupData!$AN$10 -> 353.32883 | K40: =E40*LookupData!$AN$10 -> 177.29536 | M40: =G40*LookupData!$AN$10 -> 95.524973 | N40: =H40*LookupData!$AN$10 -> 81.770386 | P40: =(M40+N40*0.75)*LookupData!AN$7 -> 14.572098 | Q40: =(M40+N40*0.75) -> 156.85276 | U40: =ROUNDUP(M40/K40,2) -> 0.54
C41: Performing Arts | D41: 112 | E41: 56.2 | G41: =(D41-LookupData!$AM$4*E41)/(LookupData!$AM$2-LookupData!$AM$4) -> 30.28 | H41: =E41-G41 -> 25.92 | J41: =D41*LookupData!$AN$10 -> 353.32883 | K41: =E41*LookupData!$AN$10 -> 177.29536 | M41: =G41*LookupData!$AN$10 -> 95.524973 | N41: =H41*LookupData!$AN$10 -> 81.770386 | P41: =(M41+N41*0.75)*LookupData!AN$7 -> 14.572098 | Q41: =(M41+N41*0.75) -> 156.85276 | U41: =ROUNDUP(M41/K41,2) -> 0.54
C42: Social_Meeting Hall | D42: 109.6 | E42: 56.1 | G42: =(D42-LookupData!$AM$4*E42)/(LookupData!$AM$2-LookupData!$AM$4) -> 28.968571 | H42: =E42-G42 -> 27.131429 | J42: =D42*LookupData!$AN$10 -> 345.7575 | K42: =E42*LookupData!$AN$10 -> 176.97989 | M42: =G42*LookupData!$AN$10 -> 91.387781 | N42: =H42*LookupData!$AN$10 -> 85.592106 | P42: =(M42+N42*0.75)*LookupData!AN$7 -> 14.454028 | Q42: =(M42+N42*0.75) -> 155.58186 | U42: =ROUNDUP(M42/K42,2) -> 0.52
C43: Stadium | D43: 112 | E43: 56.2 | G43: =(D43-LookupData!$AM$4*E43)/(LookupData!$AM$2-LookupData!$AM$4) -> 30.28 | H43: =E43-G43 -> 25.92 | J43: =D43*LookupData!$AN$10 -> 353.32883 | K43: =E43*LookupData!$AN$10 -> 177.29536 | M43: =G43*LookupData!$AN$10 -> 95.524973 | N43: =H43*LookupData!$AN$10 -> 81.770386 | P43: =(M43+N43*0.75)*LookupData!AN$7 -> 14.572098 | Q43: =(M43+N43*0.75) -> 156.85276 | U43: =ROUNDUP(M43/K43,2) -> 0.54
C44: Bar_Nightclub | D44: 297 | E44: 130.7 | G44: =(D44-LookupData!$AM$4*E44)/(LookupData!$AM$2-LookupData!$AM$4) -> 91.294286 | H44: =E44-G44 -> 39.405714 | J44: =D44*LookupData!$AN$10 -> 936.95234 | K44: =E44*LookupData!$AN$10 -> 412.32213 | M44: =G44*LookupData!$AN$10 -> 288.00806 | N44: =H44*LookupData!$AN$10 -> 124.31406 | P44: =(M44+N44*0.75)*LookupData!AN$7 -> 35.41869 | Q44: =(M44+N44*0.75) -> 381.24361 | U44: =ROUNDUP(M44/K44,2) -> 0.7
C45: Other - Entertainment | D45: 112 | E45: 56.2 | G45: =(D45-LookupData!$AM$4*E45)/(LookupData!$AM$2-LookupData!$AM$4) -> 30.28 | H45: =E45-G45 -> 25.92 | J45: =D45*LookupData!$AN$10 -> 353.32883 | K45: =E45*LookupData!$AN$10 -> 177.29536 | M45: =G45*LookupData!$AN$10 -> 95.524973 | N45: =H45*LookupData!$AN$10 -> 81.770386 | P45: =(M45+N45*0.75)*LookupData!AN$7 -> 14.572098 | Q45: =(M45+N45*0.75) -> 156.85276 | U45: =ROUNDUP(M45/K45,2) -> 0.54
B46: Recreation - Entertainment | C46: Bowling Alley | D46: 112 | E46: 50.8 | G46: =(D46-LookupData!$AM$4*E46)/(LookupData!$AM$2-LookupData!$AM$4) -> 33.52 | H46: =E46-G46 -> 17.28 | J46: =D46*LookupData!$AN$10 -> 353.32883 | K46: =E46*LookupData!$AN$10 -> 160.25986 | M46: =G46*LookupData!$AN$10 -> 105.74627 | N46: =H46*LookupData!$AN$10 -> 54.513591 | P46: =(M46+N46*0.75)*LookupData!AN$7 -> 13.622509 | Q46: =(M46+N46*0.75) -> 146.63146 | U46: =ROUNDUP(M46/K46,2) -> 0.66
C47: Roller Rink | D47: 112 | E47: 50.8 | G47: =(D47-LookupData!$AM$4*E47)/(LookupData!$AM$2-LookupData!$AM$4) -> 33.52 | H47: =E47-G47 -> 17.28 | J47: =D47*LookupData!$AN$10 -> 353.32883 | K47: =E47*LookupData!$AN$10 -> 160.25986 | M47: =G47*LookupData!$AN$10 -> 105.74627 | N47: =H47*LookupData!$AN$10 -> 54.513591 | P47: =(M47+N47*0.75)*LookupData!AN$7 -> 13.622509 | Q47: =(M47+N47*0.75) -> 146.63146 | U47: =ROUNDUP(M47/K47,2) -> 0.66
C48: Ice _ Curling Rink | D48: 112 | E48: 50.8 | G48: =(D48-LookupData!$AM$4*E48)/(LookupData!$AM$2-LookupData!$AM$4) -> 33.52 | H48: =E48-G48 -> 17.28 | J48: =D48*LookupData!$AN$10 -> 353.32883 | K48: =E48*LookupData!$AN$10 -> 160.25986 | M48: =G48*LookupData!$AN$10 -> 105.74627 | N48: =H48*LookupData!$AN$10 -> 54.513591 | P48: =(M48+N48*0.75)*LookupData!AN$7 -> 13.622509 | Q48: =(M48+N48*0.75) -> 146.63146 | U48: =ROUNDUP(M48/K48,2) -> 0.66
C49: Roller Rink | D49: 112 | E49: 50.8 | G49: =(D49-LookupData!$AM$4*E49)/(LookupData!$AM$2-LookupData!$AM$4) -> 33.52 | H49: =E49-G49 -> 17.28 | J49: =D49*LookupData!$AN$10 -> 353.32883 | K49: =E49*LookupData!$AN$10 -> 160.25986 | M49: =G49*LookupData!$AN$10 -> 105.74627 | N49: =H49*LookupData!$AN$10 -> 54.513591 | P49: =(M49+N49*0.75)*LookupData!AN$7 -> 13.622509 | Q49: =(M49+N49*0.75) -> 146.63146 | U49: =ROUNDUP(M49/K49,2) -> 0.66
C50: Swimming Pool | D50: 112 | E50: 50.8 | G50: =(D50-LookupData!$AM$4*E50)/(LookupData!$AM$2-LookupData!$AM$4) -> 33.52 | H50: =E50-G50 -> 17.28 | J50: =D50*LookupData!$AN$10 -> 353.32883 | K50: =E50*LookupData!$AN$10 -> 160.25986 | M50: =G50*LookupData!$AN$10 -> 105.74627 | N50: =H50*LookupData!$AN$10 -> 54.513591 | P50: =(M50+N50*0.75)*LookupData!AN$7 -> 13.622509 | Q50: =(M50+N50*0.75) -> 146.63146 | U50: =ROUNDUP(M50/K50,2) -> 0.66
C51: Other-Recreation | D51: 112 | E51: 50.8 | G51: =(D51-LookupData!$AM$4*E51)/(LookupData!$AM$2-LookupData!$AM$4) -> 33.52 | H51: =E51-G51 -> 17.28 | J51: =D51*LookupData!$AN$10 -> 353.32883 | K51: =E51*LookupData!$AN$10 -> 160.25986 | M51: =G51*LookupData!$AN$10 -> 105.74627 | N51: =H51*LookupData!$AN$10 -> 54.513591 | P51: =(M51+N51*0.75)*LookupData!AN$7 -> 13.622509 | Q51: =(M51+N51*0.75) -> 146.63146 | U51: =ROUNDUP(M51/K51,2) -> 0.66
B52: Food Sales and Service | C52: Convenience Store | D52: 592.6 | E52: 231.4 | G52: =(D52-LookupData!$AM$4*E52)/(LookupData!$AM$2-LookupData!$AM$4) -> 199.78857 | H52: =E52-G52 -> 31.611429 | J52: =D52*LookupData!$AN$10 -> 1869.4881 | K52: =E52*LookupData!$AN$10 -> 730.0026 | M52: =G52*LookupData!$AN$10 -> 630.27734 | N52: =H52*LookupData!$AN$10 -> 99.725259 | P52: =(M52+N52*0.75)*LookupData!AN$7 -> 65.503266 | Q52: =(M52+N52*0.75) -> 705.07128 | U52: =ROUNDUP(M52/K52,2) -> 0.87
C53: Bar_Nightclub | D53: 297 | E53: 130.7 | G53: =(D53-LookupData!$AM$4*E53)/(LookupData!$AM$2-LookupData!$AM$4) -> 91.294286 | H53: =E53-G53 -> 39.405714 | J53: =D53*LookupData!$AN$10 -> 936.95234 | K53: =E53*LookupData!$AN$10 -> 412.32213 | M53: =G53*LookupData!$AN$10 -> 288.00806 | N53: =H53*LookupData!$AN$10 -> 124.31406 | P53: =(M53+N53*0.75)*LookupData!AN$7 -> 35.41869 | Q53: =(M53+N53*0.75) -> 381.24361 | U53: =ROUNDUP(M53/K53,2) -> 0.7
C54: Fast Food Restaurant | D54: 886.4 | E54: 402.7 | G54: =(D54-LookupData!$AM$4*E54)/(LookupData!$AM$2-LookupData!$AM$4) -> 264.89429 | H54: =E54-G54 -> 137.80571 | J54: =D54*LookupData!$AN$10 -> 2796.3453 | K54: =E54*LookupData!$AN$10 -> 1270.4064 | M54: =G54*LookupData!$AN$10 -> 835.66775 | N54: =H54*LookupData!$AN$10 -> 434.73868 | P54: =(M54+N54*0.75)*LookupData!AN$7 -> 107.92748 | Q54: =(M54+N54*0.75) -> 1161.7218 | U54: =ROUNDUP(M54/K54,2) -> 0.66
C55: Restaurant | D55: 573.7 | E55: 325.6 | G55: =(D55-LookupData!$AM$4*E55)/(LookupData!$AM$2-LookupData!$AM$4) -> 132.46857 | H55: =E55-G55 -> 193.13143 | J55: =D55*LookupData!$AN$10 -> 1809.8638 | K55: =E55*LookupData!$AN$10 -> 1027.1774 | M55: =G55*LookupData!$AN$10 -> 417.90148 | N55: =H55*LookupData!$AN$10 -> 609.27591 | P55: =(M55+N55*0.75)*LookupData!AN$7 -> 81.277006 | Q55: =(M55+N55*0.75) -> 874.85841 | U55: =ROUNDUP(M55/K55,2) -> 0.41
C56: Other - Restaurant _ Bar | D56: 573.7 | E56: 325.6 | G56: =(D56-LookupData!$AM$4*E56)/(LookupData!$AM$2-LookupData!$AM$4) -> 132.46857 | H56: =E56-G56 -> 193.13143 | J56: =D56*LookupData!$AN$10 -> 1809.8638 | K56: =E56*LookupData!$AN$10 -> 1027.1774 | M56: =G56*LookupData!$AN$10 -> 417.90148 | N56: =H56*LookupData!$AN$10 -> 609.27591 | P56: =(M56+N56*0.75)*LookupData!AN$7 -> 81.277006 | Q56: =(M56+N56*0.75) -> 874.85841 | U56: =ROUNDUP(M56/K56,2) -> 0.41
C57: Supermarket_Grocery Store | D57: 444 | E57: 196 | G57: =(D57-LookupData!$AM$4*E57)/(LookupData!$AM$2-LookupData!$AM$4) -> 136.11429 | H57: =E57-G57 -> 59.885714 | J57: =D57*LookupData!$AN$10 -> 1400.6964 | K57: =E57*LookupData!$AN$10 -> 618.32545 | M57: =G57*LookupData!$AN$10 -> 429.40269 | N57: =H57*LookupData!$AN$10 -> 188.92276 | P57: =(M57+N57*0.75)*LookupData!AN$7 -> 53.056439 | Q57: =(M57+N57*0.75) -> 571.09476 | U57: =ROUNDUP(M57/K57,2) -> 0.7
C58: Wholesale Club _ Supercenter | D58: 120 | E58: 51.4 | G58: =(D58-LookupData!$AM$4*E58)/(LookupData!$AM$2-LookupData!$AM$4) -> 37.731429 | H58: =E58-G58 -> 13.668571 | J58: =D58*LookupData!$AN$10 -> 378.5666 | K58: =E58*LookupData!$AN$10 -> 162.1527 | M58: =G58*LookupData!$AN$10 -> 119.03216 | N58: =H58*LookupData!$AN$10 -> 43.120539 | P58: =(M58+N58*0.75)*LookupData!AN$7 -> 14.062971 | Q58: =(M58+N58*0.75) -> 151.37256 | U58: =ROUNDUP(M58/K58,2) -> 0.74
C59: Other - Food Sales | D59: 592.6 | E59: 231.4 | G59: =(D59-LookupData!$AM$4*E59)/(LookupData!$AM$2-LookupData!$AM$4) -> 199.78857 | H59: =E59-G59 -> 31.611429 | J59: =D59*LookupData!$AN$10 -> 1869.4881 | K59: =E59*LookupData!$AN$10 -> 730.0026 | M59: =G59*LookupData!$AN$10 -> 630.27734 | N59: =H59*LookupData!$AN$10 -> 99.725259 | P59: =(M59+N59*0.75)*LookupData!AN$7 -> 65.503266 | Q59: =(M59+N59*0.75) -> 705.07128 | U59: =ROUNDUP(M59/K59,2) -> 0.87
C60: Other - Food Service | D60: 527.7 | E60: 270.3 | G60: =(D60-LookupData!$AM$4*E60)/(LookupData!$AM$2-LookupData!$AM$4) -> 139.36286 | H60: =E60-G60 -> 130.93714 | J60: =D60*LookupData!$AN$10 -> 1664.7466 | K60: =E60*LookupData!$AN$10 -> 852.72127 | M60: =G60*LookupData!$AN$10 -> 439.65103 | N60: =H60*LookupData!$AN$10 -> 413.07024 | P60: =(M60+N60*0.75)*LookupData!AN$7 -> 69.626528 | Q60: =(M60+N60*0.75) -> 749.45371 | U60: =ROUNDUP(M60/K60,2) -> 0.52
B61: Healthcare | C61: Ambulatory Surgical Center | D61: 138.3 | E61: 62 | G61: =(D61-LookupData!$AM$4*E61)/(LookupData!$AM$2-LookupData!$AM$4) -> 41.828571 | H61: =E61-G61 -> 20.171429 | J61: =D61*LookupData!$AN$10 -> 436.29801 | K61: =E61*LookupData!$AN$10 -> 195.59274 | M61: =G61*LookupData!$AN$10 -> 131.9575 | N61: =H61*LookupData!$AN$10 -> 63.635243 | P61: =(M61+N61*0.75)*LookupData!AN$7 -> 16.693184 | Q61: =(M61+N61*0.75) -> 179.68393 | U61: =ROUNDUP(M61/K61,2) -> 0.68
C62: Hospital_General Medical Surgical | D62: 426.9 | E62: 234.3 | G62: =(D62-LookupData!$AM$4*E62)/(LookupData!$AM$2-LookupData!$AM$4) -> 103.36286 | H62: =E62-G62 -> 130.93714 | J62: =D62*LookupData!$AN$10 -> 1346.7507 | K62: =E62*LookupData!$AN$10 -> 739.15129 | M62: =G62*LookupData!$AN$10 -> 326.08105 | N62: =H62*LookupData!$AN$10 -> 413.07024 | P62: =(M62+N62*0.75)*LookupData!AN$7 -> 59.075532 | Q62: =(M62+N62*0.75) -> 635.88373 | U62: =ROUNDUP(M62/K62,2) -> 0.45
C63: Hospital_Other_Specialty | D63: 433.9 | E63: 206.7 | G63: =(D63-LookupData!$AM$4*E63)/(LookupData!$AM$2-LookupData!$AM$4) -> 123.92286 | H63: =E63-G63 -> 82.777143 | J63: =D63*LookupData!$AN$10 -> 1368.8337 | K63: =E63*LookupData!$AN$10 -> 652.08097 | M63: =G63*LookupData!$AN$10 -> 390.94213 | N63: =H63*LookupData!$AN$10 -> 261.13885 | P63: =(M63+N63*0.75)*LookupData!AN$7 -> 54.515157 | Q63: =(M63+N63*0.75) -> 586.79626 | U63: =ROUNDUP(M63/K63,2) -> 0.6
C64: Medical Office | D64: 121.7 | E64: 51.2 | G64: =(D64-LookupData!$AM$4*E64)/(LookupData!$AM$2-LookupData!$AM$4) -> 38.822857 | H64: =E64-G64 -> 12.377143 | J64: =D64*LookupData!$AN$10 -> 383.92963 | K64: =E64*LookupData!$AN$10 -> 161.52175 | M64: =G64*LookupData!$AN$10 -> 122.47531 | N64: =H64*LookupData!$AN$10 -> 39.046441 | P64: =(M64+N64*0.75)*LookupData!AN$7 -> 14.098978 | Q64: =(M64+N64*0.75) -> 151.76014 | U64: =ROUNDUP(M64/K64,2) -> 0.76
C65: Outpatient Rehabilitation_Physical Therapy | D65: 138.3 | E65: 62 | G65: =(D65-LookupData!$AM$4*E65)/(LookupData!$AM$2-LookupData!$AM$4) -> 41.828571 | H65: =E65-G65 -> 20.171429 | J65: =D65*LookupData!$AN$10 -> 436.29801 | K65: =E65*LookupData!$AN$10 -> 195.59274 | M65: =G65*LookupData!$AN$10 -> 131.9575 | N65: =H65*LookupData!$AN$10 -> 63.635243 | P65: =(M65+N65*0.75)*LookupData!AN$7 -> 16.693184 | Q65: =(M65+N65*0.75) -> 179.68393 | U65: =ROUNDUP(M65/K65,2) -> 0.68
C66: Residential Care Facility | D66: 213.2 | E66: 99 | G66: =(D66-LookupData!$AM$4*E66)/(LookupData!$AM$2-LookupData!$AM$4) -> 62.428571 | H66: =E66-G66 -> 36.571429 | J66: =D66*LookupData!$AN$10 -> 672.58666 | K66: =E66*LookupData!$AN$10 -> 312.31745 | M66: =G66*LookupData!$AN$10 -> 196.94477 | N66: =H66*LookupData!$AN$10 -> 115.37268 | P66: =(M66+N66*0.75)*LookupData!AN$7 -> 26.335622 | Q66: =(M66+N66*0.75) -> 283.47428 | U66: =ROUNDUP(M66/K66,2) -> 0.64
C67: Senior Care Community | D67: 213.2 | E67: 99 | G67: =(D67-LookupData!$AM$4*E67)/(LookupData!$AM$2-LookupData!$AM$4) -> 62.428571 | H67: =E67-G67 -> 36.571429 | J67: =D67*LookupData!$AN$10 -> 672.58666 | K67: =E67*LookupData!$AN$10 -> 312.31745 | M67: =G67*LookupData!$AN$10 -> 196.94477 | N67: =H67*LookupData!$AN$10 -> 115.37268 | P67: =(M67+N67*0.75)*LookupData!AN$7 -> 26.335622 | Q67: =(M67+N67*0.75) -> 283.47428 | U67: =ROUNDUP(M67/K67,2) -> 0.64
C68: Urgent Care _ Clinic _ Other Outpatient | D68: 145.8 | E68: 64.5 | G68: =(D68-LookupData!$AM$4*E68)/(LookupData!$AM$2-LookupData!$AM$4) -> 44.614286 | H68: =E68-G68 -> 19.885714 | J68: =D68*LookupData!$AN$10 -> 459.95842 | K68: =E68*LookupData!$AN$10 -> 203.47955 | M68: =G68*LookupData!$AN$10 -> 140.74565 | N68: =H68*LookupData!$AN$10 -> 62.733894 | P68: =(M68+N68*0.75)*LookupData!AN$7 -> 17.446826 | Q68: =(M68+N68*0.75) -> 187.79608 | U68: =ROUNDUP(M68/K68,2) -> 0.7
B69: Lodging/Residential | C69: Barracks | D69: 107.5 | E69: 57.9 | G69: =(D69-LookupData!$AM$4*E69)/(LookupData!$AM$2-LookupData!$AM$4) -> 26.688571 | H69: =E69-G69 -> 31.211429 | J69: =D69*LookupData!$AN$10 -> 339.13258 | K69: =E69*LookupData!$AN$10 -> 182.65839 | M69: =G69*LookupData!$AN$10 -> 84.195015 | N69: =H69*LookupData!$AN$10 -> 98.463371 | P69: =(M69+N69*0.75)*LookupData!AN$7 -> 14.682633 | Q69: =(M69+N69*0.75) -> 158.04254 | U69: =ROUNDUP(M69/K69,2) -> 0.47
C70: Hotel | D70: 146.7 | E70: 63 | G70: =(D70-LookupData!$AM$4*E70)/(LookupData!$AM$2-LookupData!$AM$4) -> 46.028571 | H70: =E70-G70 -> 16.971429 | J70: =D70*LookupData!$AN$10 -> 462.79767 | K70: =E70*LookupData!$AN$10 -> 198.74747 | M70: =G70*LookupData!$AN$10 -> 145.20733 | N70: =H70*LookupData!$AN$10 -> 53.540134 | P70: =(M70+N70*0.75)*LookupData!AN$7 -> 17.220734 | Q70: =(M70+N70*0.75) -> 185.36243 | U70: =ROUNDUP(M70/K70,2) -> 0.74
C71: Multifamily Housing | D71: 118.1 | E71: 59.6 | G71: =(D71-LookupData!$AM$4*E71)/(LookupData!$AM$2-LookupData!$AM$4) -> 31.725714 | H71: =E71-G71 -> 27.874286 | J71: =D71*LookupData!$AN$10 -> 372.57263 | K71: =E71*LookupData!$AN$10 -> 188.02141 | M71: =G71*LookupData!$AN$10 -> 100.0858 | N71: =H71*LookupData!$AN$10 -> 87.935614 | P71: =(M71+N71*0.75)*LookupData!AN$7 -> 15.425389 | Q71: =(M71+N71*0.75) -> 166.03751 | U71: =ROUNDUP(M71/K71,2) -> 0.54
C72: Prison_Incarceration | D72: 156.4 | E72: 69.9 | G72: =(D72-LookupData!$AM$4*E72)/(LookupData!$AM$2-LookupData!$AM$4) -> 47.431429 | H72: =E72-G72 -> 22.468571 | J72: =D72*LookupData!$AN$10 -> 493.39847 | K72: =E72*LookupData!$AN$10 -> 220.51505 | M72: =G72*LookupData!$AN$10 -> 149.63296 | N72: =H72*LookupData!$AN$10 -> 70.88209 | P72: =(M72+N72*0.75)*LookupData!AN$7 -> 18.840228 | Q72: =(M72+N72*0.75) -> 202.79452 | U72: =ROUNDUP(M72/K72,2) -> 0.68
C73: Residence Hall_Dormitory | D73: 107.5 | E73: 57.9 | G73: =(D73-LookupData!$AM$4*E73)/(LookupData!$AM$2-LookupData!$AM$4) -> 26.688571 | H73: =E73-G73 -> 31.211429 | J73: =D73*LookupData!$AN$10 -> 339.13258 | K73: =E73*LookupData!$AN$10 -> 182.65839 | M73: =G73*LookupData!$AN$10 -> 84.195015 | N73: =H73*LookupData!$AN$10 -> 98.463371 | P73: =(M73+N73*0.75)*LookupData!AN$7 -> 14.682633 | Q73: =(M73+N73*0.75) -> 158.04254 | U73: =ROUNDUP(M73/K73,2) -> 0.47
C74: Residential Care Facility | D74: 213.2 | E74: 99 | G74: =(D74-LookupData!$AM$4*E74)/(LookupData!$AM$2-LookupData!$AM$4) -> 62.428571 | H74: =E74-G74 -> 36.571429 | J74: =D74*LookupData!$AN$10 -> 672.58666 | K74: =E74*LookupData!$AN$10 -> 312.31745 | M74: =G74*LookupData!$AN$10 -> 196.94477 | N74: =H74*LookupData!$AN$10 -> 115.37268 | P74: =(M74+N74*0.75)*LookupData!AN$7 -> 26.335622 | Q74: =(M74+N74*0.75) -> 283.47428 | U74: =ROUNDUP(M74/K74,2) -> 0.64
C75: Senior Care Community | D75: 213.2 | E75: 99 | G75: =(D75-LookupData!$AM$4*E75)/(LookupData!$AM$2-LookupData!$AM$4) -> 62.428571 | H75: =E75-G75 -> 36.571429 | J75: =D75*LookupData!$AN$10 -> 672.58666 | K75: =E75*LookupData!$AN$10 -> 312.31745 | M75: =G75*LookupData!$AN$10 -> 196.94477 | N75: =H75*LookupData!$AN$10 -> 115.37268 | P75: =(M75+N75*0.75)*LookupData!AN$7 -> 26.335622 | Q75: =(M75+N75*0.75) -> 283.47428 | U75: =ROUNDUP(M75/K75,2) -> 0.64
C76: Other - Lodging _ Residential | D76: 143.6 | E76: 63.6 | G76: =(D76-LookupData!$AM$4*E76)/(LookupData!$AM$2-LookupData!$AM$4) -> 43.897143 | H76: =E76-G76 -> 19.702857 | J76: =D76*LookupData!$AN$10 -> 453.01804 | K76: =E76*LookupData!$AN$10 -> 200.6403 | M76: =G76*LookupData!$AN$10 -> 138.48327 | N76: =H76*LookupData!$AN$10 -> 62.157031 | P76: =(M76+N76*0.75)*LookupData!AN$7 -> 17.19645 | Q76: =(M76+N76*0.75) -> 185.10104 | U76: =ROUNDUP(M76/K76,2) -> 0.7
B77: Office | C77: Medical Office | D77: 121.7 | E77: 51.2 | G77: =(D77-LookupData!$AM$4*E77)/(LookupData!$AM$2-LookupData!$AM$4) -> 38.822857 | H77: =E77-G77 -> 12.377143 | J77: =D77*LookupData!$AN$10 -> 383.92963 | K77: =E77*LookupData!$AN$10 -> 161.52175 | M77: =G77*LookupData!$AN$10 -> 122.47531 | N77: =H77*LookupData!$AN$10 -> 39.046441 | P77: =(M77+N77*0.75)*LookupData!AN$7 -> 14.098978 | Q77: =(M77+N77*0.75) -> 151.76014 | U77: =ROUNDUP(M77/K77,2) -> 0.76
C78: Office | D78: 116.4 | E78: 52.9 | G78: =(D78-LookupData!$AM$4*E78)/(LookupData!$AM$2-LookupData!$AM$4) -> 34.774286 | H78: =E78-G78 -> 18.125714 | J78: =D78*LookupData!$AN$10 -> 367.20961 | K78: =E78*LookupData!$AN$10 -> 166.88478 | M78: =G78*LookupData!$AN$10 -> 109.70319 | N78: =H78*LookupData!$AN$10 -> 57.181584 | P78: =(M78+N78*0.75)*LookupData!AN$7 -> 14.176017 | Q78: =(M78+N78*0.75) -> 152.58938 | U78: =ROUNDUP(M78/K78,2) -> 0.66
C79: Veterinary Office | D79: 145.8 | E79: 64.5 | G79: =(D79-LookupData!$AM$4*E79)/(LookupData!$AM$2-LookupData!$AM$4) -> 44.614286 | H79: =E79-G79 -> 19.885714 | J79: =D79*LookupData!$AN$10 -> 459.95842 | K79: =E79*LookupData!$AN$10 -> 203.47955 | M79: =G79*LookupData!$AN$10 -> 140.74565 | N79: =H79*LookupData!$AN$10 -> 62.733894 | P79: =(M79+N79*0.75)*LookupData!AN$7 -> 17.446826 | Q79: =(M79+N79*0.75) -> 187.79608 | U79: =ROUNDUP(M79/K79,2) -> 0.7
B80: Public Services | C80: Courthouse | D80: 211.4 | E80: 101.2 | G80: =(D80-LookupData!$AM$4*E80)/(LookupData!$AM$2-LookupData!$AM$4) -> 60.08 | H80: =E80-G80 -> 41.12 | J80: =D80*LookupData!$AN$10 -> 666.90817 | K80: =E80*LookupData!$AN$10 -> 319.25784 | M80: =G80*LookupData!$AN$10 -> 189.53568 | N80: =H80*LookupData!$AN$10 -> 129.72216 | P80: =(M80+N80*0.75)*LookupData!AN$7 -> 26.647128 | Q80: =(M80+N80*0.75) -> 286.8273 | U80: =ROUNDUP(M80/K80,2) -> 0.6
C81: Fire Station | D81: 124.9 | E81: 63.5 | G81: =(D81-LookupData!$AM$4*E81)/(LookupData!$AM$2-LookupData!$AM$4) -> 33.271429 | H81: =E81-G81 -> 30.228571 | J81: =D81*LookupData!$AN$10 -> 394.02474 | K81: =E81*LookupData!$AN$10 -> 200.32483 | M81: =G81*LookupData!$AN$10 -> 104.9621 | N81: =H81*LookupData!$AN$10 -> 95.36273 | P81: =(M81+N81*0.75)*LookupData!AN$7 -> 16.395914 | Q81: =(M81+N81*0.75) -> 176.48415 | U81: =ROUNDUP(M81/K81,2) -> 0.53
C82: Library | D82: 143.6 | E82: 71.6 | G82: =(D82-LookupData!$AM$4*E82)/(LookupData!$AM$2-LookupData!$AM$4) -> 39.097143 | H82: =E82-G82 -> 32.502857 | J82: =D82*LookupData!$AN$10 -> 453.01804 | K82: =E82*LookupData!$AN$10 -> 225.87807 | M82: =G82*LookupData!$AN$10 -> 123.3406 | N82: =H82*LookupData!$AN$10 -> 102.53747 | P82: =(M82+N82*0.75)*LookupData!AN$7 -> 18.603249 | Q82: =(M82+N82*0.75) -> 200.24371 | U82: =ROUNDUP(M82/K82,2) -> 0.55
C83: Mailing Center _ Post Office | D83: 96.9 | E83: 47.9 | G83: =(D83-LookupData!$AM$4*E83)/(LookupData!$AM$2-LookupData!$AM$4) -> 26.631429 | H83: =E83-G83 -> 21.268571 | J83: =D83*LookupData!$AN$10 -> 305.69253 | K83: =E83*LookupData!$AN$10 -> 151.11117 | M83: =G83*LookupData!$AN$10 -> 84.014745 | N83: =H83*LookupData!$AN$10 -> 67.096424 | P83: =(M83+N83*0.75)*LookupData!AN$7 -> 12.480322 | Q83: =(M83+N83*0.75) -> 134.33706 | U83: =ROUNDUP(M83/K83,2) -> 0.56
C84: Police Station | D84: 124.9 | E84: 63.5 | G84: =(D84-LookupData!$AM$4*E84)/(LookupData!$AM$2-LookupData!$AM$4) -> 33.271429 | H84: =E84-G84 -> 30.228571 | J84: =D84*LookupData!$AN$10 -> 394.02474 | K84: =E84*LookupData!$AN$10 -> 200.32483 | M84: =G84*LookupData!$AN$10 -> 104.9621 | N84: =H84*LookupData!$AN$10 -> 95.36273 | P84: =(M84+N84*0.75)*LookupData!AN$7 -> 16.395914 | Q84: =(M84+N84*0.75) -> 176.48415 | U84: =ROUNDUP(M84/K84,2) -> 0.53
C85: Prison _ Incarceration | D85: 156.4 | E85: 69.9 | G85: =(D85-LookupData!$AM$4*E85)/(LookupData!$AM$2-LookupData!$AM$4) -> 47.431429 | H85: =E85-G85 -> 22.468571 | J85: =D85*LookupData!$AN$10 -> 493.39847 | K85: =E85*LookupData!$AN$10 -> 220.51505 | M85: =G85*LookupData!$AN$10 -> 149.63296 | N85: =H85*LookupData!$AN$10 -> 70.88209 | P85: =(M85+N85*0.75)*LookupData!AN$7 -> 18.840228 | Q85: =(M85+N85*0.75) -> 202.79452 | U85: =ROUNDUP(M85/K85,2) -> 0.68
C86: Social_Meeting Hall | D86: 109.6 | E86: 56.1 | G86: =(D86-LookupData!$AM$4*E86)/(LookupData!$AM$2-LookupData!$AM$4) -> 28.968571 | H86: =E86-G86 -> 27.131429 | J86: =D86*LookupData!$AN$10 -> 345.7575 | K86: =E86*LookupData!$AN$10 -> 176.97989 | M86: =G86*LookupData!$AN$10 -> 91.387781 | N86: =H86*LookupData!$AN$10 -> 85.592106 | P86: =(M86+N86*0.75)*LookupData!AN$7 -> 14.454028 | Q86: =(M86+N86*0.75) -> 155.58186 | U86: =ROUNDUP(M86/K86,2) -> 0.52
C87: Transportation Terminal _ Station | D87: 112 | E87: 56.2 | G87: =(D87-LookupData!$AM$4*E87)/(LookupData!$AM$2-LookupData!$AM$4) -> 30.28 | H87: =E87-G87 -> 25.92 | J87: =D87*LookupData!$AN$10 -> 353.32883 | K87: =E87*LookupData!$AN$10 -> 177.29536 | M87: =G87*LookupData!$AN$10 -> 95.524973 | N87: =H87*LookupData!$AN$10 -> 81.770386 | P87: =(M87+N87*0.75)*LookupData!AN$7 -> 14.572098 | Q87: =(M87+N87*0.75) -> 156.85276 | U87: =ROUNDUP(M87/K87,2) -> 0.54
C88: Other - Public Services | D88: 89.3 | E88: 40.1 | G88: =(D88-LookupData!$AM$4*E88)/(LookupData!$AM$2-LookupData!$AM$4) -> 26.968571 | H88: =E88-G88 -> 13.131429 | J88: =D88*LookupData!$AN$10 -> 281.71665 | K88: =E88*LookupData!$AN$10 -> 126.50434 | M88: =G88*LookupData!$AN$10 -> 85.078337 | N88: =H88*LookupData!$AN$10 -> 41.426003 | P88: =(M88+N88*0.75)*LookupData!AN$7 -> 10.790487 | Q88: =(M88+N88*0.75) -> 116.14784 | U88: =ROUNDUP(M88/K88,2) -> 0.68
B89: Religious Worship | C89: Worship Facility | D89: 58.4 | E89: 30.5 | G89: =(D89-LookupData!$AM$4*E89)/(LookupData!$AM$2-LookupData!$AM$4) -> 15.071429 | H89: =E89-G89 -> 15.428571 | J89: =D89*LookupData!$AN$10 -> 184.23575 | K89: =E89*LookupData!$AN$10 -> 96.219012 | M89: =G89*LookupData!$AN$10 -> 47.546163 | N89: =H89*LookupData!$AN$10 -> 48.672849 | P89: =(M89+N89*0.75)*LookupData!AN$7 -> 7.8085748 | Q89: =(M89+N89*0.75) -> 84.050799 | U89: =ROUNDUP(M89/K89,2) -> 0.5
B90: Retail | C90: Automotive Dealership | D90: 124.1 | E90: 55 | G90: =(D90-LookupData!$AM$4*E90)/(LookupData!$AM$2-LookupData!$AM$4) -> 37.914286 | H90: =E90-G90 -> 17.085714 | J90: =D90*LookupData!$AN$10 -> 391.50096 | K90: =E90*LookupData!$AN$10 -> 173.50969 | M90: =G90*LookupData!$AN$10 -> 119.60902 | N90: =H90*LookupData!$AN$10 -> 53.900673 | P90: =(M90+N90*0.75)*LookupData!AN$7 -> 14.867694 | Q90: =(M90+N90*0.75) -> 160.03452 | U90: =ROUNDUP(M90/K90,2) -> 0.69
C91: Convenience Store | D91: 592.6 | E91: 231.4 | G91: =(D91-LookupData!$AM$4*E91)/(LookupData!$AM$2-LookupData!$AM$4) -> 199.78857 | H91: =E91-G91 -> 31.611429 | J91: =D91*LookupData!$AN$10 -> 1869.4881 | K91: =E91*LookupData!$AN$10 -> 730.0026 | M91: =G91*LookupData!$AN$10 -> 630.27734 | N91: =H91*LookupData!$AN$10 -> 99.725259 | P91: =(M91+N91*0.75)*LookupData!AN$7 -> 65.503266 | Q91: =(M91+N91*0.75) -> 705.07128 | U91: =ROUNDUP(M91/K91,2) -> 0.87
C92: Enclosed Mall | D92: 170.7 | E92: 65.7 | G92: =(D92-LookupData!$AM$4*E92)/(LookupData!$AM$2-LookupData!$AM$4) -> 58.122857 | H92: =E92-G92 -> 7.5771429 | J92: =D92*LookupData!$AN$10 -> 538.51099 | K92: =E92*LookupData!$AN$10 -> 207.26522 | M92: =G92*LookupData!$AN$10 -> 183.36144 | N92: =H92*LookupData!$AN$10 -> 23.903777 | P92: =(M92+N92*0.75)*LookupData!AN$7 -> 18.700385 | Q92: =(M92+N92*0.75) -> 201.28927 | U92: =ROUNDUP(M92/K92,2) -> 0.89
C93: Mall - Lifestyle Center | D93: 228.8 | E93: 103.5 | G93: =(D93-LookupData!$AM$4*E93)/(LookupData!$AM$2-LookupData!$AM$4) -> 68.642857 | H93: =E93-G93 -> 34.857143 | J93: =D93*LookupData!$AN$10 -> 721.80032 | K93: =E93*LookupData!$AN$10 -> 326.5137 | M93: =G93*LookupData!$AN$10 -> 216.54911 | N93: =H93*LookupData!$AN$10 -> 109.96458 | P93: =(M93+N93*0.75)*LookupData!AN$7 -> 27.780104 | Q93: =(M93+N93*0.75) -> 299.02255 | U93: =ROUNDUP(M93/K93,2) -> 0.67
C94: Strip Mall | D94: 228.8 | E94: 103.5 | G94: =(D94-LookupData!$AM$4*E94)/(LookupData!$AM$2-LookupData!$AM$4) -> 68.642857 | H94: =E94-G94 -> 34.857143 | J94: =D94*LookupData!$AN$10 -> 721.80032 | K94: =E94*LookupData!$AN$10 -> 326.5137 | M94: =G94*LookupData!$AN$10 -> 216.54911 | N94: =H94*LookupData!$AN$10 -> 109.96458 | P94: =(M94+N94*0.75)*LookupData!AN$7 -> 27.780104 | Q94: =(M94+N94*0.75) -> 299.02255 | U94: =ROUNDUP(M94/K94,2) -> 0.67
C95: Other - Mall | D95: 225.3 | E95: 101.6 | G95: =(D95-LookupData!$AM$4*E95)/(LookupData!$AM$2-LookupData!$AM$4) -> 67.782857 | H95: =E95-G95 -> 33.817143 | J95: =D95*LookupData!$AN$10 -> 710.7588 | K95: =E95*LookupData!$AN$10 -> 320.51972 | M95: =G95*LookupData!$AN$10 -> 213.83605 | N95: =H95*LookupData!$AN$10 -> 106.68367 | P95: =(M95+N95*0.75)*LookupData!AN$7 -> 27.299447 | Q95: =(M95+N95*0.75) -> 293.84881 | U95: =ROUNDUP(M95/K95,2) -> 0.67
C96: Retail Store | D96: 120 | E96: 51.4 | G96: =(D96-LookupData!$AM$4*E96)/(LookupData!$AM$2-LookupData!$AM$4) -> 37.731429 | H96: =E96-G96 -> 13.668571 | J96: =D96*LookupData!$AN$10 -> 378.5666 | K96: =E96*LookupData!$AN$10 -> 162.1527 | M96: =G96*LookupData!$AN$10 -> 119.03216 | N96: =H96*LookupData!$AN$10 -> 43.120539 | P96: =(M96+N96*0.75)*LookupData!AN$7 -> 14.062971 | Q96: =(M96+N96*0.75) -> 151.37256 | U96: =ROUNDUP(M96/K96,2) -> 0.74
C97: Supermarket_Grocery Store | D97: 444 | E97: 196 | G97: =(D97-LookupData!$AM$4*E97)/(LookupData!$AM$2-LookupData!$AM$4) -> 136.11429 | H97: =E97-G97 -> 59.885714 | J97: =D97*LookupData!$AN$10 -> 1400.6964 | K97: =E97*LookupData!$AN$10 -> 618.32545 | M97: =G97*LookupData!$AN$10 -> 429.40269 | N97: =H97*LookupData!$AN$10 -> 188.92276 | P97: =(M97+N97*0.75)*LookupData!AN$7 -> 53.056439 | Q97: =(M97+N97*0.75) -> 571.09476 | U97: =ROUNDUP(M97/K97,2) -> 0.7
C98: Wholesale Club _ Supercenter | D98: 120 | E98: 51.4 | G98: =(D98-LookupData!$AM$4*E98)/(LookupData!$AM$2-LookupData!$AM$4) -> 37.731429 | H98: =E98-G98 -> 13.668571 | J98: =D98*LookupData!$AN$10 -> 378.5666 | K98: =E98*LookupData!$AN$10 -> 162.1527 | M98: =G98*LookupData!$AN$10 -> 119.03216 | N98: =H98*LookupData!$AN$10 -> 43.120539 | P98: =(M98+N98*0.75)*LookupData!AN$7 -> 14.062971 | Q98: =(M98+N98*0.75) -> 151.37256 | U98: =ROUNDUP(M98/K98,2) -> 0.74
B99: Technology / Science | C99: Laboratory | D99: 318.2 | E99: 115.3 | G99: =(D99-LookupData!$AM$4*E99)/(LookupData!$AM$2-LookupData!$AM$4) -> 112.64857 | H99: =E99-G99 -> 2.6514286 | J99: =D99*LookupData!$AN$10 -> 1003.8324 | K99: =E99*LookupData!$AN$10 -> 363.73941 | M99: =G99*LookupData!$AN$10 -> 355.37489 | N99: =H99*LookupData!$AN$10 -> 8.3645192 | P99: =(M99+N99*0.75)*LookupData!AN$7 -> 33.598225 | Q99: =(M99+N99*0.75) -> 361.64828
C100: Other - Technology Science | D100: 89.3 | E100: 40.1 | G100: =(D100-LookupData!$AM$4*E100)/(LookupData!$AM$2-LookupData!$AM$4) -> 26.968571 | H100: =E100-G100 -> 13.131429 | J100: =D100*LookupData!$AN$10 -> 281.71665 | K100: =E100*LookupData!$AN$10 -> 126.50434 | M100: =G100*LookupData!$AN$10 -> 85.078337 | N100: =H100*LookupData!$AN$10 -> 41.426003 | P100: =(M100+N100*0.75)*LookupData!AN$7 -> 10.790487 | Q100: =(M100+N100*0.75) -> 116.14784 | U100: =ROUNDUP(M100/K100,2) -> 0.68
B101: Services | C101: Personal Services_Health_Beauty_Dry Cleaning | D101: 96.9 | E101: 47.9 | G101: =(D101-LookupData!$AM$4*E101)/(LookupData!$AM$2-LookupData!$AM$4) -> 26.631429 | H101: =E101-G101 -> 21.268571 | J101: =D101*LookupData!$AN$10 -> 305.69253 | K101: =E101*LookupData!$AN$10 -> 151.11117 | M101: =G101*LookupData!$AN$10 -> 84.014745 | N101: =H101*LookupData!$AN$10 -> 67.096424 | P101: =(M101+N101*0.75)*LookupData!AN$7 -> 12.480322 | Q101: =(M101+N101*0.75) -> 134.33706
C102: Repair Services_Vehicle, Shoe, Locksmith, etc. | D102: 96.9 | E102: 47.9 | G102: =(D102-LookupData!$AM$4*E102)/(LookupData!$AM$2-LookupData!$AM$4) -> 26.631429 | H102: =E102-G102 -> 21.268571 | J102: =D102*LookupData!$AN$10 -> 305.69253 | K102: =E102*LookupData!$AN$10 -> 151.11117 | M102: =G102*LookupData!$AN$10 -> 84.014745 | N102: =H102*LookupData!$AN$10 -> 67.096424 | P102: =(M102+N102*0.75)*LookupData!AN$7 -> 12.480322 | Q102: =(M102+N102*0.75) -> 134.33706 | U102: =ROUNDUP(M102/K102,2) -> 0.56
C103: Other-Services | D103: 96.9 | E103: 47.9 | G103: =(D103-LookupData!$AM$4*E103)/(LookupData!$AM$2-LookupData!$AM$4) -> 26.631429 | H103: =E103-G103 -> 21.268571 | J103: =D103*LookupData!$AN$10 -> 305.69253 | K103: =E103*LookupData!$AN$10 -> 151.11117 | M103: =G103*LookupData!$AN$10 -> 84.014745 | N103: =H103*LookupData!$AN$10 -> 67.096424 | P103: =(M103+N103*0.75)*LookupData!AN$7 -> 12.480322 | Q103: =(M103+N103*0.75) -> 134.33706 | U103: =ROUNDUP(M103/K103,2) -> 0.56
B104: Utility | C104: Energy_Power Station | D104: 89.3 | E104: 40.1 | G104: =(D104-LookupData!$AM$4*E104)/(LookupData!$AM$2-LookupData!$AM$4) -> 26.968571 | H104: =E104-G104 -> 13.131429 | J104: =D104*LookupData!$AN$10 -> 281.71665 | K104: =E104*LookupData!$AN$10 -> 126.50434 | M104: =G104*LookupData!$AN$10 -> 85.078337 | N104: =H104*LookupData!$AN$10 -> 41.426003 | P104: =(M104+N104*0.75)*LookupData!AN$7 -> 10.790487 | Q104: =(M104+N104*0.75) -> 116.14784 | U104: =ROUNDUP(M104/K104,2) -> 0.68
C105: Other - Utility | D105: 89.3 | E105: 40.1 | G105: =(D105-LookupData!$AM$4*E105)/(LookupData!$AM$2-LookupData!$AM$4) -> 26.968571 | H105: =E105-G105 -> 13.131429 | J105: =D105*LookupData!$AN$10 -> 281.71665 | K105: =E105*LookupData!$AN$10 -> 126.50434 | M105: =G105*LookupData!$AN$10 -> 85.078337 | N105: =H105*LookupData!$AN$10 -> 41.426003 | P105: =(M105+N105*0.75)*LookupData!AN$7 -> 10.790487 | Q105: =(M105+N105*0.75) -> 116.14784 | U105: =ROUNDUP(M105/K105,2) -> 0.68
B106: Warehouse/Storate | C106: Self-storage Facility | D106: 47.8 | E106: 20.2 | G106: =(D106-LookupData!$AM$4*E106)/(LookupData!$AM$2-LookupData!$AM$4) -> 15.194286 | H106: =E106-G106 -> 5.0057143 | J106: =D106*LookupData!$AN$10 -> 150.7957 | K106: =E106*LookupData!$AN$10 -> 63.725378 | M106: =G106*LookupData!$AN$10 -> 47.933743 | N106: =H106*LookupData!$AN$10 -> 15.791635 | P106: =(M106+N106*0.75)*LookupData!AN$7 -> 5.5535086 | Q106: =(M106+N106*0.75) -> 59.777469 | U106: =ROUNDUP(M106/K106,2) -> 0.76
C107: Warehouse _ Distribution Center | D107: 52.9 | E107: 22.7 | G107: =(D107-LookupData!$AM$4*E107)/(LookupData!$AM$2-LookupData!$AM$4) -> 16.608571 | H107: =E107-G107 -> 6.0914286 | J107: =D107*LookupData!$AN$10 -> 166.88478 | K107: =E107*LookupData!$AN$10 -> 71.612182 | M107: =G107*LookupData!$AN$10 -> 52.395421 | N107: =H107*LookupData!$AN$10 -> 19.216762 | P107: =(M107+N107*0.75)*LookupData!AN$7 -> 6.2066656 | Q107: =(M107+N107*0.75) -> 66.807992 | U107: =ROUNDUP(M107/K107,2) -> 0.74
C108: Non-refrigerated Warehouse | D108: 52.9 | E108: 22.7 | G108: =(D108-LookupData!$AM$4*E108)/(LookupData!$AM$2-LookupData!$AM$4) -> 16.608571 | H108: =E108-G108 -> 6.0914286 | J108: =D108*LookupData!$AN$10 -> 166.88478 | K108: =E108*LookupData!$AN$10 -> 71.612182 | M108: =G108*LookupData!$AN$10 -> 52.395421 | N108: =H108*LookupData!$AN$10 -> 19.216762 | P108: =(M108+N108*0.75)*LookupData!AN$7 -> 6.2066656 | Q108: =(M108+N108*0.75) -> 66.807992 | U108: =ROUNDUP(M108/K108,2) -> 0.74
C109: Refrigerated Warehouse | D109: 235.6 | E109: 84.1 | G109: =(D109-LookupData!$AM$4*E109)/(LookupData!$AM$2-LookupData!$AM$4) -> 84.168571 | H109: =E109-G109 -> -0.068571429 | J109: =D109*LookupData!$AN$10 -> 743.25243 | K109: =E109*LookupData!$AN$10 -> 265.31209 | M109: =K109 -> 265.31209 | P109: =(M109+N109*0.75)*LookupData!AN$7 -> 24.6483 | Q109: =(M109+N109*0.75) -> 265.31209 | U109: =ROUNDUP(M109/K109,2) -> 1
...

Sheet Summary
C3: Summary for Design and Construction Rating Systems
C4: Note: All information on this tab is READ-ONLY. To edit, see previous tabs.
C9: EA Credit Renewable Energy
C11: Tier 1: On-site renewable energy percent of annual project site energy use | H11: ='Renewable Energy'!T38 -> 0
C13: Tier 2. New Off-site renewable electricity percent of annual project site energy use | H13: ='Renewable Energy'!T39 -> 0
C15: Tier 3. Off-site renewable percent of annual project site energy use | H15: ='Renewable Energy'!T40 -> 0
C17: Points: | G17: =IFERROR(IF('Renewable Energy'!L42>0,'Renewable Energy'!L42,""),"") | H17: =IFERROR('Renewable Energy'!M42,"") -> Points

Sheet LookupData
A1: LEED Renewable Category | D1: Energy Generation Type | E1: Offset Energy type | G1: Energy Consumption Units | H1: convert to kWh | M1: Renewable Generator Location | Q1: Procurement Type | R1: Tier 1 | S1: Tier 2 | T1: Tier 3 | V1: Tier 1 On-site renewable sources | W1: Generation Type | Y1: Tier 2 Renewable Electricity Generation Sources | AA1: Tier 3 Renewable Generation Sources | AB1: Offset Energy type | AE1: Length of Contract (Years) | AI1: DD-Month-YY | AL1: Source-to-Site Ratios | AQ1: Table 1. Points for Renewable Energy Procurement - BD+C | AX1: Table 2. Points for CS | BD1: Table 3. Points for Renewable Energy Procurement - ID+C | BJ1: Rating System | BM1: Selected Rating System: | BQ1: Tier 1 | BR1: Tier 2 | BS1: Tier 3 | BU1: Total | BV1: EP?
A2: Tier 1. On-site renewable energy | B2: On-site renewable generation, environmental attributes (e.g. RECs) retained | D2: Electricity | E2: Electricity | G2: kWh | H2: 1 | M2: Tier 1 | N2: Tier 2 | O2: Tier 3 | Q2: Owned | R2: Owned | S2: Virtual Power Purchase Agreement (VPPA) | T2: Unbundled: Green-e EACs | V2: Photovoltaic | W2: Electricity | Y2: Photovoltaic | AA2: Photovoltaic | AB2: Electricity | AE2: One-time purchase | AF2: 1 | AL2: Electricity (Grid Purchase) | AM2: 2.8 | AQ2: Points | AR2: Tier 1 | AS2: Tier 2 | AT2: Tier 3 | AU2: NC Points | AX2: Points | AY2: Tier 1 | AZ2: Tier 2 | BA2: Tier 3 | BD2: Points | BE2: Tier 1 | BF2: Tier 2 | BG2: Tier 3 | BH2: ID+C Points | BJ2: BD+C: New Construction | BK2: BDC | BM2: {=IFERROR(VLOOKUP(Instructions!$H$12,TableRatingSystem,2,FALSE),BDC)} -> BDC | BP2: Percent | BQ2: ='Renewable Energy'!$T$38 -> 0 | BR2: ='Renewable Energy'!$T$39 -> 0 | BS2: ='Renewable Energy'!$T$40 -> 0 | BU2: ='Renewable Energy'!$T$42 -> 0
A3: Tier 2. New Off-site renewable electricity | B3: Off-site renewable electricity produced by generation asset(s) built within the last 5 years or contracted to be operational within 2 years of building occupancy | D3: Thermal | E3: Fossil Fuel | G3: MWh | H3: 1000 | M3: 1 | N3: 2 | O3: 3 | Q3: Leased | R3: Leased | S3: Feed-in Tariff | T3: Unbundled: Green-e equivalent EACs* | V3: Wind | W3: Electricity | Y3: Wind | AA3: Wind | AB3: Electricity | AE3: more than 10 | AF3: 10 | AL3: Electricity - On-site Wind or Solar | AM3: 1 | AQ3: 0 | AR3: 0 | AS3: 0 | AT3: 0 | AU3: =AQ3 -> 0 | AX3: 0 | AY3: 0 | AZ3: 0 | BA3: 0 | BB3: =AX3 -> 0 | BD3: 0 | BE3: 0 | BF3: 0 | BG3: 0 | BH3: =BD3 -> 0 | BJ3: BD+C: Core and Shell | BK3: CS | BP3: Points | BQ3: =IF($BM$2="CS",BQ$6,IF($BM$2="IDC",BQ$7,BQ$5)) | BR3: =IF($BM$2="CS",BR$6,IF($BM$2="IDC",BR$7,BR$5)) | BS3: =IF($BM$2="CS",BS$6,IF($BM$2="IDC",BS$7,BS$5)) | BU3: =IFERROR(IF($BM$2="CS",BU$6,IF($BM$2="IDC",BU$7,BU$5)),"") -> 0 | BV3: =IF($BM$2="CS",BV$6,IF($BM$2="IDC",BV$7,BV$5))
A4: Tier 3. Off-site renewable energy | B4: Off-site renewable electricity that is Green-e Energy certified or equivalent or captured bio-methane | E4: District Cooling | G4: kBtu | H4: 0.29308324 | M4: On site | N4: same country | O4: same country | Q4: Power Purchase Agreement (PPA) | R4: Power Purchase Agreement (PPA) | S4: Power Purchase Agreement (PPA) | T4: Utility 100% Green Power Tariff | V4: Solar thermal | W4: Thermal | Y4: Solar thermal electricity | AA4: Solar thermal electricity | AB4: Electricity | AE4: 10 | AF4: 10 | AL4: Natural Gas | AM4: 1.05 | AQ4: 0.1 | AR4: 0.0015 | AS4: =AQ4/10-0.0005 -> 0.0095 | AT4: =AU4*AT$13-0.0005 -> 0.03445 | AU4: =AQ4 -> 0.1 | AX4: =AX3+0.2 -> 0.2 | AY4: 0.0015 | AZ4: 0.0055 | BA4: 0.0195 | BB4: =AX4 -> 0.2 | BD4: 0.1 | BE4: 0.0015 | BF4: =BD4/10-0.0005 -> 0.0095 | BG4: =BH4*BG$13-0.0005 -> 0.02445 | BH4: =BD4 -> 0.1 | BJ4: BD+C: Schools | BK4: BDC
E5: District Heating | G5: therm | H5: 29.308324 | M5: On campus | N5: Same geographical region | O5: Same geographical region | Q5: Virtual Power Purchase Agreement (VPPA) | R5: Other-Describe | S5: Utility 100% Green Power Tariff | T5: Virtual Power Purchase Agreement (VPPA) | V5: On-site untreated wood waste - thermal* | W5: Thermal | Y5: Geothermal electricity* | AA5: Geothermal electricity* | AB5: Electricity | AE5: 9 | AF5: 9 | AQ5: =AQ4+0.1 -> 0.2 | AR5: 0.0035 | AS5: =AQ5/10-0.0005 -> 0.0195 | AT5: =AT4+2.5% -> 0.05945 | AU5: =AQ5 -> 0.2 | AX5: =AX4+0.2 -> 0.4 | AY5: 0.0035 | AZ5: 0.0115 | BA5: 0.0395 | BB5: =AX5 -> 0.4 | BD5: =BD4+0.1 -> 0.2 | BE5: 0.0035 | BF5: =BD5/10-0.0005 -> 0.0195 | BG5: =BG4+2.5% -> 0.04945 | BH5: =BD5 -> 0.2 | BJ5: BD+C: Retail | BK5: BDC | BP5: Points BDC | BQ5: =IFERROR(IF(BQ$2>0,VLOOKUP(BQ$2,Lookup_Tier1_Points,4),""),"") | BR5: =IFERROR(IF(BR$2>0,VLOOKUP(BR$2,Lookup_Tier2_Points,3),""),"") | BS5: =IFERROR(IF(BS$2>0,VLOOKUP(BS$2,Lookup_Tier3_Points,2),""),"") | BU5: =IFERROR(MIN(ROUNDDOWN(SUM(BQ5:BS5),0),5),"") -> 0 | BV5: =IF(OR($BQ$2>=25%,$BR$2>=60%,SUM(BQ5:BR5)>=6),"EP","")
E6: Other | G6: Btu x 10^6 | H6: 293.08324 | M6: Other - Describe | N6: Other - Describe | O6: Other - Describe | Q6: Feed-in Tariff | S6: Unbundled: Green-e EACs | T6: Feed-in Tariff | V6: On-site agricultural crops or waste - thermal* | W6: Thermal | Y6: Ocean-based (wave/tidal)* | AA6: Ocean-based (wave/tidal)* | AB6: Electricity | AE6: 8 | AF6: 8 | AQ6: =AQ5+0.1 -> 0.3 | AR6: 0.0055 | AS6: =AQ6/10-0.0005 -> 0.0295 | AT6: =AT5+2.5% -> 0.08445 | AU6: =AQ6 -> 0.3 | AX6: =AX5+0.2 -> 0.6 | AY6: 0.0055 | AZ6: 0.0175 | BA6: 0.0595 | BB6: =AX6 -> 0.6 | BD6: =BD5+0.1 -> 0.3 | BE6: 0.0055 | BF6: =BD6/10-0.0005 -> 0.0295 | BG6: =BG5+2.5% -> 0.07445 | BH6: =BD6 -> 0.3 | BJ6: BD+C: Healthcare | BK6: BDC | BP6: Points CS | BQ6: =IFERROR(IF(BQ$2>0,VLOOKUP(BQ$2,$AY$3:$BB$28,4),""),"") | BR6: =IFERROR(IF(BR$2>0,VLOOKUP(BR$2,$AZ$3:$BB$28,3),""),"") | BS6: =IFERROR(IF(BS$2>0,VLOOKUP(BS$2,$BA$3:$BB$18,2),""),"") | BU6: =IFERROR(MIN(ROUNDDOWN(SUM(BQ6:BS6),0),5),"") -> 0 | BV6: =IF(OR($BQ$2>=25%,$BR$2>=60%),"EP","")
G7: MJ | H7: 0.27784291 | Q7: Utility 100% Green Power Tariff | S7: Unbundled: Green-e equivalent EACs* | T7: Power Purchase Agreement (PPA) | V7: On-site animal or organic waste - thermal* | W7: Thermal | Y7: Low-impact hydropower* | AA7: Low-impact hydropower* | AB7: Electricity | AE7: 7 | AF7: 7 | AL7: IP Units | AM7: ft2 to m2 | AN7: =CONVERT(1,"ft","m")^2 -> 0.09290304 | AQ7: =AQ6+0.1 -> 0.4 | AR7: 0.0075 | AS7: =AQ7/10-0.0005 -> 0.0395 | AT7: =AT6+2.5% -> 0.10945 | AU7: =AQ7 -> 0.4 | AX7: =AX6+0.2 -> 0.8 | AY7: 0.0075 | AZ7: 0.0235 | BA7: 0.0795 | BB7: =AX7 -> 0.8 | BD7: =BD6+0.1 -> 0.4 | BE7: 0.0075 | BF7: =BD7/10-0.0005 -> 0.0395 | BG7: =BG6+2.5% -> 0.09945 | BH7: =BD7 -> 0.4 | BJ7: BD+C: Data Centers | BK7: BDC | BP7: Points IDC | BQ7: =IFERROR(IF(BQ$2>0,VLOOKUP(BQ$2,BE3:BH63,4),""),"") | BR7: =IFERROR(IF(BR$2>0,VLOOKUP(BR$2,BF3:BH63,3),""),"") | BS7: =IFERROR(IF(BS$2>0,VLOOKUP(BS$2,BG3:BH43,2),""),"") | BU7: =IFERROR(MIN(ROUNDDOWN(SUM(BQ7:BS7),0),6),"") -> 0 | BV7: =IF(OR($BQ$2>=30%,$BR$2>=70%,SUM(BQ7:BR7)>=7),"EP","")
G8: Ton Hours | H8: 3.5169988 | Q8: Unbundled: Green-e EACs | S8: Leased | T8: Leased | V8: On-site landfill gas - thermal* | W8: Thermal | Y8: Biofuel electricity* | AA8: Biofuel electricity* | AB8: Electricity | AE8: 6 | AF8: 6 | AM8: kBtu to kWh | AN8: =1/3.412 -> 0.29308324 | AQ8: =AQ7+0.1 -> 0.5 | AR8: 0.0095 | AS8: =AQ8/10-0.0005 -> 0.0495 | AT8: =AT7+2.5% -> 0.13445 | AU8: =AQ8 -> 0.5 | AX8: =AX7+0.2 -> 1 | AY8: 0.0095 | AZ8: 0.0295 | BA8: 0.0995 | BB8: =AX8 -> 1 | BD8: =BD7+0.1 -> 0.5 | BE8: 0.0095 | BF8: =BD8/10-0.0005 -> 0.0495 | BG8: =BG7+2.5% -> 0.12445 | BH8: =BD8 -> 0.5 | BJ8: BD+C: Hospitality | BK8: BDC
Q9: Unbundled: Green-e equivalent EACs* | S9: Owned | T9: Owned | V9: Geothermal heating (not geoexchange) | W9: Thermal | Y9: Other - Decribe* | AA9: Renewable electricity mix | AB9: Electricity | AE9: 5 | AF9: 5 | AQ9: =AQ8+0.1 -> 0.6 | AR9: 0.0115 | AS9: =AQ9/10-0.0005 -> 0.0595 | AT9: =AT8+2.5% -> 0.15945 | AU9: =AQ9 -> 0.6 | AX9: =AX8+0.2 -> 1.2 | AY9: 0.0135 | AZ9: 0.0355 | BA9: 0.1195 | BB9: =AX9 -> 1.2 | BD9: =BD8+0.1 -> 0.6 | BE9: 0.0115 | BF9: =BD9/10-0.0005 -> 0.0595 | BG9: =BG8+2.5% -> 0.14945 | BH9: =BD9 -> 0.6 | BJ9: BD+C: Warehouses and Distribution | BK9: BDC
G10: =IF(IP_SI_Units="IP Units","kWh","kWh") -> kWh | H10: Default Electricity | Q10: Other - Describe | S10: Other - Describe | T10: Other - Describe | V10: On-site untreated wood waste - electric | W10: Electricity | AA10: Recovered bio-methane* | AB10: =E3 -> Fossil Fuel | AE10: 4 | AF10: 4 | AM10: kbtu/ft2 to kWh/m2 | AN10: =AN8/AN7 -> 3.1547217 | AQ10: =AQ9+0.1 -> 0.7 | AR10: 0.0135 | AS10: =AQ10/10-0.0005 -> 0.0695 | AT10: =AT9+2.5% -> 0.18445 | AU10: =AQ10 -> 0.7 | AX10: =AX9+0.2 -> 1.4 | AY10: 0.0175 | AZ10: 0.0415 | BA10: 0.1395 | BB10: =AX10 -> 1.4 | BD10: =BD9+0.1 -> 0.7 | BE10: 0.0135 | BF10: =BD10/10-0.0005 -> 0.0695 | BG10: =BG9+2.5% -> 0.17445 | BH10: =BD10 -> 0.7 | BJ10: ID+C: Commercial Interiors | BK10: IDC
G11: =IF(IP_SI_Units="IP Units","therm","kWh") -> therm | H11: Default Fossil Fuel | V11: On-site agricultural crops or waste - electric | W11: Electricity | AA11: Other - Decribe* | AE11: 3 | AF11: 3 | AQ11: =AQ10+0.1 -> 0.8 | AR11: 0.0155 | AS11: =AQ11/10-0.0005 -> 0.0795 | AT11: =AT10+2.5% -> 0.20945 | AU11: =AQ11 -> 0.8 | AX11: =AX10+0.2 -> 1.6 | AY11: 0.0215 | AZ11: 0.0475 | BA11: 0.1595 | BB11: =AX11 -> 1.6 | BD11: =BD10+0.1 -> 0.8 | BE11: 0.0155 | BF11: =BD11/10-0.0005 -> 0.0795 | BG11: =BG10+2.5% -> 0.19945 | BH11: =BD11 -> 0.8 | BJ11: ID+C: Retail | BK11: IDC
G12: =IF(IP_SI_Units="IP Units","Ton Hours","kWh") -> Ton Hours | H12: Default District Cooling | V12: On-site animal or organic waste - electric | W12: Electricity | AE12: 2 | AF12: 2 | AQ12: =AQ11+0.1 -> 0.9 | AR12: 0.0175 | AS12: =AQ12/10-0.0005 -> 0.0895 | AT12: =AT11+2.5% -> 0.23445 | AU12: =AQ12 -> 0.9 | AX12: =AX11+0.2 -> 1.8 | AY12: 0.0255 | AZ12: 0.0535 | BA12: 0.1795 | BB12: =AX12 -> 1.8 | BD12: =BD11+0.1 -> 0.9 | BE12: 0.0175 | BF12: =BD12/10-0.0005 -> 0.0895 | BG12: =BG11+2.5% -> 0.22445 | BH12: =BD12 -> 0.9 | BJ12: ID+C: Hospitality | BK12: IDC
G13: =IF(IP_SI_Units="IP Units","kBtu","kWh") -> kBtu | H13: Default District Heating | V13: On-site landfill gas - electric | W13: Electricity | AE13: 1 | AF13: 1 | AQ13: =AQ12+0.1 -> 1 | AR13: =2%-0.0005 -> 0.0195 | AS13: =AQ13/10-0.0005 -> 0.0995 | AT13: =35%-0.0005 -> 0.3495 | AU13: =AQ13 -> 1 | AX13: =AX12+0.2 -> 2 | AY13: 0.0295 | AZ13: 0.0595 | BA13: 0.1995 | BB13: =AX13 -> 2 | BD13: =BD12+0.1 -> 1 | BE13: =2%-0.0005 -> 0.0195 | BF13: =BD13/10-0.0005 -> 0.0995 | BG13: =25%-0.0005 -> 0.2495 | BH13: =BD13 -> 1
V14: Geothermal electric | W14: Electricity | AE14: N/A (owned) | AF14: 10 | AQ14: =AQ13+0.1 -> 1.1 | AR14: 0.0225 | AS14: =AQ14/10-0.0005 -> 0.1095 | AT14: =AT13+2.5% -> 0.3745 | AU14: =AQ14 -> 1.1 | AX14: =AX13+0.2 -> 2.2 | AY14: 0.0335 | AZ14: 0.0655 | BA14: 0.2195 | BB14: =AX14 -> 2.2 | BD14: =BD13+0.1 -> 1.1 | BE14: 0.0225 | BF14: =BD14/10-0.0005 -> 0.1095 | BG14: =BG13+2.5% -> 0.2745 | BH14: =BD14 -> 1.1
G15: =IF(IP_SI_Units="IP Units","Btu x 10^6","MWh") -> Btu x 10^6 | H15: Default Total | V15: Other - Describe | AQ15: =AQ14+0.1 -> 1.2 | AR15: 0.0255 | AS15: =AQ15/10-0.0005 -> 0.1195 | AT15: =AT14+2.5% -> 0.3995 | AU15: =AQ15 -> 1.2 | AX15: =AX14+0.2 -> 2.4 | AY15: 0.0375 | AZ15: 0.0715 | BA15: 0.2395 | BB15: =AX15 -> 2.4 | BD15: =BD14+0.1 -> 1.2 | BE15: 0.0255 | BF15: =BD15/10-0.0005 -> 0.1195 | BG15: =BG14+2.5% -> 0.2995 | BH15: =BD15 -> 1.2
AQ16: =AQ15+0.1 -> 1.3 | AR16: 0.0285 | AS16: =AQ16/10-0.0005 -> 0.1295 | AT16: =AT15+2.5% -> 0.4245 | AU16: =AQ16 -> 1.3 | AX16: =AX15+0.2 -> 2.6 | AY16: 0.0415 | AZ16: 0.0775 | BA16: 0.2595 | BB16: =AX16 -> 2.6 | BD16: =BD15+0.1 -> 1.3 | BE16: 0.0285 | BF16: =BD16/10-0.0005 -> 0.1295 | BG16: =BG15+2.5% -> 0.3245 | BH16: =BD16 -> 1.3
AQ17: =AQ16+0.1 -> 1.4 | AR17: 0.0315 | AS17: =AQ17/10-0.0005 -> 0.1395 | AT17: =AT16+2.5% -> 0.4495 | AU17: =AQ17 -> 1.4 | AX17: =AX16+0.2 -> 2.8 | AY17: 0.0455 | AZ17: 0.0835 | BA17: 0.2795 | BB17: =AX17 -> 2.8 | BD17: =BD16+0.1 -> 1.4 | BE17: 0.0315 | BF17: =BD17/10-0.0005 -> 0.1395 | BG17: =BG16+2.5% -> 0.3495 | BH17: =BD17 -> 1.4
AQ18: =AQ17+0.1 -> 1.5 | AR18: 0.0345 | AS18: =AQ18/10-0.0005 -> 0.1495 | AT18: =AT17+2.5% -> 0.4745 | AU18: =AQ18 -> 1.5 | AX18: =AX17+0.2 -> 3 | AY18: 0.0495 | AZ18: 0.0895 | BA18: 0.2995 | BB18: =AX18 -> 3 | BD18: =BD17+0.1 -> 1.5 | BE18: 0.0345 | BF18: =BD18/10-0.0005 -> 0.1495 | BG18: =BG17+2.5% -> 0.3745 | BH18: =BD18 -> 1.5
AM19: 0.05 | AN19: =AS5+10% -> 0.1195 | AO19: 0.7 | AP19: 2 | AQ19: =AQ18+0.1 -> 1.6 | AR19: 0.0375 | AS19: =AQ19/10-0.0005 -> 0.1595 | AT19: =AT18+2.5% -> 0.4995 | AU19: =AQ19 -> 1.6 | AX19: =AX18+0.2 -> 3.2 | AY19: 0.0595 | AZ19: 0.0955 | BB19: =AX19 -> 3.2 | BD19: =BD18+0.1 -> 1.6 | BE19: 0.0375 | BF19: =BD19/10-0.0005 -> 0.1595 | BG19: =BG18+2.5% -> 0.3995 | BH19: =BD19 -> 1.6
V20: All Renewabe Sources | AM20: 0.1 | AN20: =AN19+10% -> 0.2195 | AO20: 1 | AP20: 3 | AQ20: =AQ19+0.1 -> 1.7 | AR20: 0.0405 | AS20: =AQ20/10-0.0005 -> 0.1695 | AT20: =AT19+2.5% -> 0.5245 | AU20: =AQ20 -> 1.7 | AX20: =AX19+0.2 -> 3.4 | AY20: 0.0695 | AZ20: 0.1015 | BB20: =AX20 -> 3.4 | BD20: =BD19+0.1 -> 1.7 | BE20: 0.0405 | BF20: =BD20/10-0.0005 -> 0.1695 | BG20: =BG19+2.5% -> 0.4245 | BH20: =BD20 -> 1.7
V21: Photovoltaic | W21: Electricity | AM21: 0.15 | AN21: =AN20+10% -> 0.3195 | AP21: 4 | AQ21: =AQ20+0.1 -> 1.8 | AR21: 0.0435 | AS21: =AQ21/10-0.0005 -> 0.1795 | AT21: =AT20+2.5% -> 0.5495 | AU21: =AQ21 -> 1.8 | AX21: =AX20+0.2 -> 3.6 | AY21: 0.0795 | AZ21: 0.1075 | BB21: =AX21 -> 3.6 | BD21: =BD20+0.1 -> 1.8 | BE21: 0.0435 | BF21: =BD21/10-0.0005 -> 0.1795 | BG21: =BG20+2.5% -> 0.4495 | BH21: =BD21 -> 1.8
V22: Wind | W22: Electricity | AM22: 0.2 | AN22: =AN21+10% -> 0.4195 | AP22: 5 | AQ22: =AQ21+0.1 -> 1.9 | AR22: 0.0465 | AS22: =AQ22/10-0.0005 -> 0.1895 | AT22: =AT21+2.5% -> 0.5745 | AU22: =AQ22 -> 1.9 | AX22: =AX21+0.2 -> 3.8 | AY22: 0.0895 | AZ22: 0.1135 | BB22: =AX22 -> 3.8 | BD22: =BD21+0.1 -> 1.9 | BE22: 0.0465 | BF22: =BD22/10-0.0005 -> 0.1895 | BG22: =BG21+2.5% -> 0.4745 | BH22: =BD22 -> 1.9
V23: Solar thermal | W23: Thermal | AM23: 0.25 | AN23: =AN22+10% -> 0.5195 | AP23: Exemplary | AQ23: =AQ22+0.1 -> 2 | AR23: =5%-0.0005 -> 0.0495 | AS23: =AQ23/10-0.0005 -> 0.1995 | AT23: =70%-0.0005 -> 0.6995 | AU23: =AQ23 -> 2 | AX23: =AX22+0.2 -> 4 | AY23: 0.0995 | AZ23: 0.1195 | BB23: =AX23 -> 4 | BD23: =BD22+0.1 -> 2 | BE23: =5%-0.0005 -> 0.0495 | BF23: =BD23/10-0.0005 -> 0.1995 | BG23: =50%-0.0005 -> 0.4995 | BH23: =BD23 -> 2
V24: On-site untreated wood waste - thermal* | W24: Thermal | AQ24: =AQ23+0.1 -> 2.1 | AR24: =AR23+0.5% -> 0.0545 | AS24: =AQ24/10-0.0005 -> 0.2095 | AT24: =AT23+2.5% -> 0.7245 | AU24: =AQ24 -> 2.1 | AX24: =AX23+0.2 -> 4.2 | AY24: 0.1095 | AZ24: 0.1255 | BB24: =AX24 -> 4.2 | BD24: =BD23+0.1 -> 2.1 | BE24: =BE23+0.5% -> 0.0545 | BF24: =BD24/10-0.0005 -> 0.2095 | BG24: =BG23+2.5% -> 0.5245 | BH24: =BD24 -> 2.1
V25: On-site agricultural crops or waste - thermal* | W25: Thermal | AQ25: =AQ24+0.1 -> 2.2 | AR25: =AR24+0.5% -> 0.0595 | AS25: =AQ25/10-0.0005 -> 0.2195 | AT25: =AT24+2.5% -> 0.7495 | AU25: =AQ25 -> 2.2 | AX25: =AX24+0.2 -> 4.4 | AY25: 0.1195 | AZ25: 0.1315 | BB25: =AX25 -> 4.4 | BD25: =BD24+0.1 -> 2.2 | BE25: =BE24+0.5% -> 0.0595 | BF25: =BD25/10-0.0005 -> 0.2195 | BG25: =BG24+2.5% -> 0.5495 | BH25: =BD25 -> 2.2
V26: On-site animal or organic waste - thermal* | W26: Thermal | AQ26: =AQ25+0.1 -> 2.3 | AR26: =AR25+0.5% -> 0.0645 | AS26: =AQ26/10-0.0005 -> 0.2295 | AT26: =AT25+2.5% -> 0.7745 | AU26: =AQ26 -> 2.3 | AX26: =AX25+0.2 -> 4.6 | AY26: 0.1295 | AZ26: 0.1375 | BB26: =AX26 -> 4.6 | BD26: =BD25+0.1 -> 2.3 | BE26: =BE25+0.5% -> 0.0645 | BF26: =BD26/10-0.0005 -> 0.2295 | BG26: =BG25+2.5% -> 0.5745 | BH26: =BD26 -> 2.3
V27: On-site landfill gas - thermal* | W27: Thermal | AQ27: =AQ26+0.1 -> 2.4 | AR27: =AR26+0.5% -> 0.0695 | AS27: =AQ27/10-0.0005 -> 0.2395 | AT27: =AT26+2.5% -> 0.7995 | AU27: =AQ27 -> 2.4 | AX27: =AX26+0.2 -> 4.8 | AY27: 0.1395 | AZ27: 0.1435 | BB27: =AX27 -> 4.8 | BD27: =BD26+0.1 -> 2.4 | BE27: =BE26+0.5% -> 0.0695 | BF27: =BD27/10-0.0005 -> 0.2395 | BG27: =BG26+2.5% -> 0.5995 | BH27: =BD27 -> 2.4
V28: Geothermal heating (not geoexchange) | W28: Thermal | AQ28: =AQ27+0.1 -> 2.5 | AR28: =AR27+0.5% -> 0.0745 | AS28: =AQ28/10-0.0005 -> 0.2495 | AT28: =AT27+2.5% -> 0.8245 | AU28: =AQ28 -> 2.5 | AX28: =AX27+0.2 -> 5 | AY28: 0.1495 | AZ28: 0.1495 | BB28: =AX28 -> 5 | BD28: =BD27+0.1 -> 2.5 | BE28: =BE27+0.5% -> 0.0745 | BF28: =BD28/10-0.0005 -> 0.2495 | BG28: =BG27+2.5% -> 0.6245 | BH28: =BD28 -> 2.5
V29: On-site untreated wood waste - electric | W29: Electricity | AQ29: =AQ28+0.1 -> 2.6 | AR29: =AR28+0.5% -> 0.0795 | AS29: =AQ29/10-0.0005 -> 0.2595 | AT29: =AT28+2.5% -> 0.8495 | AU29: =AQ29 -> 2.6 | BD29: =BD28+0.1 -> 2.6 | BE29: =BE28+0.5% -> 0.0795 | BF29: =BD29/10-0.0005 -> 0.2595 | BG29: =BG28+2.5% -> 0.6495 | BH29: =BD29 -> 2.6
V30: On-site agricultural crops or waste - electric | W30: Electricity | AQ30: =AQ29+0.1 -> 2.7 | AR30: =AR29+0.5% -> 0.0845 | AS30: =AQ30/10-0.0005 -> 0.2695 | AT30: =AT29+2.5% -> 0.8745 | AU30: =AQ30 -> 2.7 | BD30: =BD29+0.1 -> 2.7 | BE30: =BE29+0.5% -> 0.0845 | BF30: =BD30/10-0.0005 -> 0.2695 | BG30: =BG29+2.5% -> 0.6745 | BH30: =BD30 -> 2.7
V31: On-site animal or organic waste - electric | W31: Electricity | AQ31: =AQ30+0.1 -> 2.8 | AR31: =AR30+0.5% -> 0.0895 | AS31: =AQ31/10-0.0005 -> 0.2795 | AT31: =AT30+2.5% -> 0.8995 | AU31: =AQ31 -> 2.8 | BD31: =BD30+0.1 -> 2.8 | BE31: =BE30+0.5% -> 0.0895 | BF31: =BD31/10-0.0005 -> 0.2795 | BG31: =BG30+2.5% -> 0.6995 | BH31: =BD31 -> 2.8
V32: On-site landfill gas - electric | W32: Electricity | AQ32: =AQ31+0.1 -> 2.9 | AR32: =AR31+0.5% -> 0.0945 | AS32: =AQ32/10-0.0005 -> 0.2895 | AT32: =AT31+2.5% -> 0.9245 | AU32: =AQ32 -> 2.9 | BD32: =BD31+0.1 -> 2.9 | BE32: =BE31+0.5% -> 0.0945 | BF32: =BD32/10-0.0005 -> 0.2895 | BG32: =BG31+2.5% -> 0.7245 | BH32: =BD32 -> 2.9
V33: Geothermal electric | W33: Electricity | AQ33: =AQ32+0.1 -> 3 | AR33: =AR32+0.5% -> 0.0995 | AS33: =AQ33/10-0.0005 -> 0.2995 | AT33: =100%-0.0005 -> 0.9995 | AU33: =AQ33 -> 3 | BD33: =BD32+0.1 -> 3 | BE33: =BE32+0.5% -> 0.0995 | BF33: =BD33/10-0.0005 -> 0.2995 | BG33: =75%-0.0005 -> 0.7495 | BH33: =BD33 -> 3
V34: Solar thermal electricity | W34: Electricity | AQ34: =AQ33+0.1 -> 3.1 | AR34: =AR33+0.5% -> 0.1045 | AS34: =AQ34/10-0.0005 -> 0.3095 | AU34: =AQ34 -> 3.1 | BD34: =BD33+0.1 -> 3.1 | BE34: =BE33+0.5% -> 0.1045 | BF34: =BD34/10-0.0005 -> 0.3095 | BG34: =BG33+2.5% -> 0.7745 | BH34: =BD34 -> 3.1
V35: Geothermal electricity* | W35: Electricity | AQ35: =AQ34+0.1 -> 3.2 | AR35: =AR34+0.5% -> 0.1095 | AS35: =AQ35/10-0.0005 -> 0.3195 | AU35: =AQ35 -> 3.2 | BD35: =BD34+0.1 -> 3.2 | BE35: =BE34+0.5% -> 0.1095 | BF35: =BD35/10-0.0005 -> 0.3195 | BG35: =BG34+2.5% -> 0.7995 | BH35: =BD35 -> 3.2
V36: Ocean-based (wave/tidal)* | W36: Electricity | AQ36: =AQ35+0.1 -> 3.3 | AR36: =AR35+0.5% -> 0.1145 | AS36: =AQ36/10-0.0005 -> 0.3295 | AU36: =AQ36 -> 3.3 | BD36: =BD35+0.1 -> 3.3 | BE36: =BE35+0.5% -> 0.1145 | BF36: =BD36/10-0.0005 -> 0.3295 | BG36: =BG35+2.5% -> 0.8245 | BH36: =BD36 -> 3.3
V37: Low-impact hydropower* | W37: Electricity | AQ37: =AQ36+0.1 -> 3.4 | AR37: =AR36+0.5% -> 0.1195 | AS37: =AQ37/10-0.0005 -> 0.3395 | AU37: =AQ37 -> 3.4 | BD37: =BD36+0.1 -> 3.4 | BE37: =BE36+0.5% -> 0.1195 | BF37: =BD37/10-0.0005 -> 0.3395 | BG37: =BG36+2.5% -> 0.8495 | BH37: =BD37 -> 3.4
V38: Biofuel electricity* | W38: Electricity | AQ38: =AQ37+0.1 -> 3.5 | AR38: =AR37+0.5% -> 0.1245 | AS38: =AQ38/10-0.0005 -> 0.3495 | AU38: =AQ38 -> 3.5 | BD38: =BD37+0.1 -> 3.5 | BE38: =BE37+0.5% -> 0.1245 | BF38: =BD38/10-0.0005 -> 0.3495 | BG38: =BG37+2.5% -> 0.8745 | BH38: =BD38 -> 3.5
V39: Green-e certified electricity mix | W39: Electricity | AQ39: =AQ38+0.1 -> 3.6 | AR39: =AR38+0.5% -> 0.1295 | AS39: =AQ39/10-0.0005 -> 0.3595 | AU39: =AQ39 -> 3.6 | BD39: =BD38+0.1 -> 3.6 | BE39: =BE38+0.5% -> 0.1295 | BF39: =BD39/10-0.0005 -> 0.3595 | BG39: =BG38+2.5% -> 0.8995 | BH39: =BD39 -> 3.6
V40: Recovered bio-methane* | W40: =E3 -> Fossil Fuel | AQ40: =AQ39+0.1 -> 3.7 | AR40: =AR39+0.5% -> 0.1345 | AS40: =AQ40/10-0.0005 -> 0.3695 | AU40: =AQ40 -> 3.7 | BD40: =BD39+0.1 -> 3.7 | BE40: =BE39+0.5% -> 0.1345 | BF40: =BD40/10-0.0005 -> 0.3695 | BG40: =BG39+2.5% -> 0.9245 | BH40: =BD40 -> 3.7
V41: Other - Describe | AQ41: =AQ40+0.1 -> 3.8 | AR41: =AR40+0.5% -> 0.1395 | AS41: =AQ41/10-0.0005 -> 0.3795 | AU41: =AQ41 -> 3.8 | BD41: =BD40+0.1 -> 3.8 | BE41: =BE40+0.5% -> 0.1395 | BF41: =BD41/10-0.0005 -> 0.3795 | BG41: =BG40+2.5% -> 0.9495 | BH41: =BD41 -> 3.8
AQ42: =AQ41+0.1 -> 3.9 | AR42: =AR41+0.5% -> 0.1445 | AS42: =AQ42/10-0.0005 -> 0.3895 | AU42: =AQ42 -> 3.9 | BD42: =BD41+0.1 -> 3.9 | BE42: =BE41+0.5% -> 0.1445 | BF42: =BD42/10-0.0005 -> 0.3895 | BG42: =BG41+2.5% -> 0.9745 | BH42: =BD42 -> 3.9
AQ43: =AQ42+0.1 -> 4 | AR43: =AR42+0.5% -> 0.1495 | AS43: =AQ43/10-0.0005 -> 0.3995 | AU43: =AQ43 -> 4 | BD43: =BD42+0.1 -> 4 | BE43: =BE42+0.5% -> 0.1495 | BF43: =BD43/10-0.0005 -> 0.3995 | BG43: =100%-0.0005 -> 0.9995 | BH43: =BD43 -> 4
AQ44: =AQ43+0.1 -> 4.1 | AR44: =AR43+0.5% -> 0.1545 | AS44: =AQ44/10-0.0005 -> 0.4095 | AU44: =AQ44 -> 4.1 | BD44: =BD43+0.1 -> 4.1 | BE44: =BE43+0.5% -> 0.1545 | BF44: =BD44/10-0.0005 -> 0.4095 | BH44: =BD44 -> 4.1
AQ45: =AQ44+0.1 -> 4.2 | AR45: =AR44+0.5% -> 0.1595 | AS45: =AQ45/10-0.0005 -> 0.4195 | AU45: =AQ45 -> 4.2 | BD45: =BD44+0.1 -> 4.2 | BE45: =BE44+0.5% -> 0.1595 | BF45: =BD45/10-0.0005 -> 0.4195 | BH45: =BD45 -> 4.2
AQ46: =AQ45+0.1 -> 4.3 | AR46: =AR45+0.5% -> 0.1645 | AS46: =AQ46/10-0.0005 -> 0.4295 | AU46: =AQ46 -> 4.3 | BD46: =BD45+0.1 -> 4.3 | BE46: =BE45+0.5% -> 0.1645 | BF46: =BD46/10-0.0005 -> 0.4295 | BH46: =BD46 -> 4.3
AQ47: =AQ46+0.1 -> 4.4 | AR47: =AR46+0.5% -> 0.1695 | AS47: =AQ47/10-0.0005 -> 0.4395 | AU47: =AQ47 -> 4.4 | BD47: =BD46+0.1 -> 4.4 | BE47: =BE46+0.5% -> 0.1695 | BF47: =BD47/10-0.0005 -> 0.4395 | BH47: =BD47 -> 4.4
AQ48: =AQ47+0.1 -> 4.5 | AR48: =AR47+0.5% -> 0.1745 | AS48: =AQ48/10-0.0005 -> 0.4495 | AU48: =AQ48 -> 4.5 | BD48: =BD47+0.1 -> 4.5 | BE48: =BE47+0.5% -> 0.1745 | BF48: =BD48/10-0.0005 -> 0.4495 | BH48: =BD48 -> 4.5
AQ49: =AQ48+0.1 -> 4.6 | AR49: =AR48+0.5% -> 0.1795 | AS49: =AQ49/10-0.0005 -> 0.4595 | AU49: =AQ49 -> 4.6 | BD49: =BD48+0.1 -> 4.6 | BE49: =BE48+0.5% -> 0.1795 | BF49: =BD49/10-0.0005 -> 0.4595 | BH49: =BD49 -> 4.6
AQ50: =AQ49+0.1 -> 4.7 | AR50: =AR49+0.5% -> 0.1845 | AS50: =AQ50/10-0.0005 -> 0.4695 | AU50: =AQ50 -> 4.7 | BD50: =BD49+0.1 -> 4.7 | BE50: =BE49+0.5% -> 0.1845 | BF50: =BD50/10-0.0005 -> 0.4695 | BH50: =BD50 -> 4.7
AQ51: =AQ50+0.1 -> 4.8 | AR51: =AR50+0.5% -> 0.1895 | AS51: =AQ51/10-0.0005 -> 0.4795 | AU51: =AQ51 -> 4.8 | BD51: =BD50+0.1 -> 4.8 | BE51: =BE50+0.5% -> 0.1895 | BF51: =BD51/10-0.0005 -> 0.4795 | BH51: =BD51 -> 4.8
AQ52: =AQ51+0.1 -> 4.9 | AR52: =AR51+0.5% -> 0.1945 | AS52: =AQ52/10-0.0005 -> 0.4895 | AU52: =AQ52 -> 4.9 | BD52: =BD51+0.1 -> 4.9 | BE52: =BE51+0.5% -> 0.1945 | BF52: =BD52/10-0.0005 -> 0.4895 | BH52: =BD52 -> 4.9
AQ53: =AQ52+0.1 -> 5 | AR53: =AR52+0.5% -> 0.1995 | AS53: =AQ53/10-0.0005 -> 0.4995 | AU53: =AQ53 -> 5 | BD53: =BD52+0.1 -> 5 | BE53: =BE52+0.5% -> 0.1995 | BF53: =BD53/10-0.0005 -> 0.4995 | BH53: =BD53 -> 5
BD54: =BD53+0.1 -> 5.1 | BE54: =BE53+0.5% -> 0.2045 | BF54: =BD54/10-0.0005 -> 0.5095 | BH54: =BD54 -> 5.1
BD55: =BD54+0.1 -> 5.2 | BE55: =BE54+0.5% -> 0.2095 | BF55: =BD55/10-0.0005 -> 0.5195 | BH55: =BD55 -> 5.2
BD56: =BD55+0.1 -> 5.3 | BE56: =BE55+0.5% -> 0.2145 | BF56: =BD56/10-0.0005 -> 0.5295 | BH56: =BD56 -> 5.3
BD57: =BD56+0.1 -> 5.4 | BE57: =BE56+0.5% -> 0.2195 | BF57: =BD57/10-0.0005 -> 0.5395 | BH57: =BD57 -> 5.4
BD58: =BD57+0.1 -> 5.5 | BE58: =BE57+0.5% -> 0.2245 | BF58: =BD58/10-0.0005 -> 0.5495 | BH58: =BD58 -> 5.5
BD59: =BD58+0.1 -> 5.6 | BE59: =BE58+0.5% -> 0.2295 | BF59: =BD59/10-0.0005 -> 0.5595 | BH59: =BD59 -> 5.6
BD60: =BD59+0.1 -> 5.7 | BE60: =BE59+0.5% -> 0.2345 | BF60: =BD60/10-0.0005 -> 0.5695 | BH60: =BD60 -> 5.7
BD61: =BD60+0.1 -> 5.8 | BE61: =BE60+0.5% -> 0.2395 | BF61: =BD61/10-0.0005 -> 0.5795 | BH61: =BD61 -> 5.8
BD62: =BD61+0.1 -> 5.9 | BE62: =BE61+0.5% -> 0.2445 | BF62: =BD62/10-0.0005 -> 0.5895 | BH62: =BD62 -> 5.9
BD63: 6 | BE63: =BE62+0.5% -> 0.2495 | BF63: =BD63/10-0.0005 -> 0.5995 | BH63: =BD63 -> 6
